[
  {
    "PassengerId":306,
    "Survived":"1",
    "Pclass":1,
    "Sex":"male",
    "Age":0.92,
    "Fare":151.55
  },
  {
    "PassengerId":298,
    "Survived":"0",
    "Pclass":1,
    "Sex":"female",
    "Age":2,
    "Fare":151.55
  },
  {
    "PassengerId":446,
    "Survived":"1",
    "Pclass":1,
    "Sex":"male",
    "Age":4,
    "Fare":81.8583
  },
  {
    "PassengerId":803,
    "Survived":"1",
    "Pclass":1,
    "Sex":"male",
    "Age":11,
    "Fare":120
  },
  {
    "PassengerId":436,
    "Survived":"1",
    "Pclass":1,
    "Sex":"female",
    "Age":14,
    "Fare":120
  },
  {
    "PassengerId":690,
    "Survived":"1",
    "Pclass":1,
    "Sex":"female",
    "Age":15,
    "Fare":211.3375
  },
  {
    "PassengerId":854,
    "Survived":"1",
    "Pclass":1,
    "Sex":"female",
    "Age":16,
    "Fare":39.4
  },
  {
    "PassengerId":330,
    "Survived":"1",
    "Pclass":1,
    "Sex":"female",
    "Age":16,
    "Fare":57.9792
  },
  {
    "PassengerId":505,
    "Survived":"1",
    "Pclass":1,
    "Sex":"female",
    "Age":16,
    "Fare":86.5
  },
  {
    "PassengerId":782,
    "Survived":"1",
    "Pclass":1,
    "Sex":"female",
    "Age":17,
    "Fare":57
  },
  {
    "PassengerId":308,
    "Survived":"1",
    "Pclass":1,
    "Sex":"female",
    "Age":17,
    "Fare":108.9
  },
  {
    "PassengerId":551,
    "Survived":"1",
    "Pclass":1,
    "Sex":"male",
    "Age":17,
    "Fare":110.8833
  },
  {
    "PassengerId":586,
    "Survived":"1",
    "Pclass":1,
    "Sex":"female",
    "Age":18,
    "Fare":79.65
  },
  {
    "PassengerId":506,
    "Survived":"0",
    "Pclass":1,
    "Sex":"male",
    "Age":18,
    "Fare":108.9
  },
  {
    "PassengerId":701,
    "Survived":"1",
    "Pclass":1,
    "Sex":"female",
    "Age":18,
    "Fare":227.525
  },
  {
    "PassengerId":312,
    "Survived":"1",
    "Pclass":1,
    "Sex":"female",
    "Age":18,
    "Fare":262.375
  },
  {
    "PassengerId":137,
    "Survived":"1",
    "Pclass":1,
    "Sex":"female",
    "Age":19,
    "Fare":26.2833
  },
  {
    "PassengerId":888,
    "Survived":"1",
    "Pclass":1,
    "Sex":"female",
    "Age":19,
    "Fare":30
  },
  {
    "PassengerId":749,
    "Survived":"0",
    "Pclass":1,
    "Sex":"male",
    "Age":19,
    "Fare":53.1
  },
  {
    "PassengerId":292,
    "Survived":"1",
    "Pclass":1,
    "Sex":"female",
    "Age":19,
    "Fare":91.0792
  },
  {
    "PassengerId":28,
    "Survived":"0",
    "Pclass":1,
    "Sex":"male",
    "Age":19,
    "Fare":263
  },
  {
    "PassengerId":103,
    "Survived":"0",
    "Pclass":1,
    "Sex":"male",
    "Age":21,
    "Fare":77.2875
  },
  {
    "PassengerId":628,
    "Survived":"1",
    "Pclass":1,
    "Sex":"female",
    "Age":21,
    "Fare":77.9583
  },
  {
    "PassengerId":743,
    "Survived":"1",
    "Pclass":1,
    "Sex":"female",
    "Age":21,
    "Fare":262.375
  },
  {
    "PassengerId":540,
    "Survived":"1",
    "Pclass":1,
    "Sex":"female",
    "Age":22,
    "Fare":49.5
  },
  {
    "PassengerId":357,
    "Survived":"1",
    "Pclass":1,
    "Sex":"female",
    "Age":22,
    "Fare":55
  },
  {
    "PassengerId":152,
    "Survived":"1",
    "Pclass":1,
    "Sex":"female",
    "Age":22,
    "Fare":66.6
  },
  {
    "PassengerId":374,
    "Survived":"0",
    "Pclass":1,
    "Sex":"male",
    "Age":22,
    "Fare":135.6333
  },
  {
    "PassengerId":709,
    "Survived":"1",
    "Pclass":1,
    "Sex":"female",
    "Age":22,
    "Fare":151.55
  },
  {
    "PassengerId":98,
    "Survived":"1",
    "Pclass":1,
    "Sex":"male",
    "Age":23,
    "Fare":63.3583
  },
  {
    "PassengerId":394,
    "Survived":"1",
    "Pclass":1,
    "Sex":"female",
    "Age":23,
    "Fare":113.275
  },
  {
    "PassengerId":89,
    "Survived":"1",
    "Pclass":1,
    "Sex":"female",
    "Age":23,
    "Fare":263
  },
  {
    "PassengerId":711,
    "Survived":"1",
    "Pclass":1,
    "Sex":"female",
    "Age":24,
    "Fare":49.5042
  },
  {
    "PassengerId":642,
    "Survived":"1",
    "Pclass":1,
    "Sex":"female",
    "Age":24,
    "Fare":69.3
  },
  {
    "PassengerId":370,
    "Survived":"1",
    "Pclass":1,
    "Sex":"female",
    "Age":24,
    "Fare":69.3
  },
  {
    "PassengerId":140,
    "Survived":"0",
    "Pclass":1,
    "Sex":"male",
    "Age":24,
    "Fare":79.2
  },
  {
    "PassengerId":311,
    "Survived":"1",
    "Pclass":1,
    "Sex":"female",
    "Age":24,
    "Fare":83.1583
  },
  {
    "PassengerId":119,
    "Survived":"0",
    "Pclass":1,
    "Sex":"male",
    "Age":24,
    "Fare":247.5208
  },
  {
    "PassengerId":342,
    "Survived":"1",
    "Pclass":1,
    "Sex":"female",
    "Age":24,
    "Fare":263
  },
  {
    "PassengerId":371,
    "Survived":"1",
    "Pclass":1,
    "Sex":"male",
    "Age":25,
    "Fare":55.4417
  },
  {
    "PassengerId":485,
    "Survived":"1",
    "Pclass":1,
    "Sex":"male",
    "Age":25,
    "Fare":91.0792
  },
  {
    "PassengerId":499,
    "Survived":"0",
    "Pclass":1,
    "Sex":"female",
    "Age":25,
    "Fare":151.55
  },
  {
    "PassengerId":890,
    "Survived":"1",
    "Pclass":1,
    "Sex":"male",
    "Age":26,
    "Fare":30
  },
  {
    "PassengerId":291,
    "Survived":"1",
    "Pclass":1,
    "Sex":"female",
    "Age":26,
    "Fare":78.85
  },
  {
    "PassengerId":608,
    "Survived":"1",
    "Pclass":1,
    "Sex":"male",
    "Age":27,
    "Fare":30.5
  },
  {
    "PassengerId":725,
    "Survived":"1",
    "Pclass":1,
    "Sex":"male",
    "Age":27,
    "Fare":53.1
  },
  {
    "PassengerId":682,
    "Survived":"1",
    "Pclass":1,
    "Sex":"male",
    "Age":27,
    "Fare":76.7292
  },
  {
    "PassengerId":378,
    "Survived":"0",
    "Pclass":1,
    "Sex":"male",
    "Age":27,
    "Fare":211.5
  },
  {
    "PassengerId":431,
    "Survived":"1",
    "Pclass":1,
    "Sex":"male",
    "Age":28,
    "Fare":26.55
  },
  {
    "PassengerId":24,
    "Survived":"1",
    "Pclass":1,
    "Sex":"male",
    "Age":28,
    "Fare":35.5
  },
  {
    "PassengerId":84,
    "Survived":"0",
    "Pclass":1,
    "Sex":"male",
    "Age":28,
    "Fare":47.1
  },
  {
    "PassengerId":35,
    "Survived":"0",
    "Pclass":1,
    "Sex":"male",
    "Age":28,
    "Fare":82.1708
  },
  {
    "PassengerId":783,
    "Survived":"0",
    "Pclass":1,
    "Sex":"male",
    "Age":29,
    "Fare":30
  },
  {
    "PassengerId":337,
    "Survived":"0",
    "Pclass":1,
    "Sex":"male",
    "Age":29,
    "Fare":66.6
  },
  {
    "PassengerId":731,
    "Survived":"1",
    "Pclass":1,
    "Sex":"female",
    "Age":29,
    "Fare":211.3375
  },
  {
    "PassengerId":453,
    "Survived":"0",
    "Pclass":1,
    "Sex":"male",
    "Age":30,
    "Fare":27.75
  },
  {
    "PassengerId":843,
    "Survived":"1",
    "Pclass":1,
    "Sex":"female",
    "Age":30,
    "Fare":31
  },
  {
    "PassengerId":310,
    "Survived":"1",
    "Pclass":1,
    "Sex":"female",
    "Age":30,
    "Fare":56.9292
  },
  {
    "PassengerId":258,
    "Survived":"1",
    "Pclass":1,
    "Sex":"female",
    "Age":30,
    "Fare":86.5
  },
  {
    "PassengerId":521,
    "Survived":"1",
    "Pclass":1,
    "Sex":"female",
    "Age":30,
    "Fare":93.5
  },
  {
    "PassengerId":538,
    "Survived":"1",
    "Pclass":1,
    "Sex":"female",
    "Age":30,
    "Fare":106.425
  },
  {
    "PassengerId":868,
    "Survived":"0",
    "Pclass":1,
    "Sex":"male",
    "Age":31,
    "Fare":50.4958
  },
  {
    "PassengerId":672,
    "Survived":"0",
    "Pclass":1,
    "Sex":"male",
    "Age":31,
    "Fare":52
  },
  {
    "PassengerId":691,
    "Survived":"1",
    "Pclass":1,
    "Sex":"male",
    "Age":31,
    "Fare":57
  },
  {
    "PassengerId":216,
    "Survived":"1",
    "Pclass":1,
    "Sex":"female",
    "Age":31,
    "Fare":113.275
  },
  {
    "PassengerId":319,
    "Survived":"1",
    "Pclass":1,
    "Sex":"female",
    "Age":31,
    "Fare":164.8667
  },
  {
    "PassengerId":633,
    "Survived":"1",
    "Pclass":1,
    "Sex":"male",
    "Age":32,
    "Fare":30.5
  },
  {
    "PassengerId":219,
    "Survived":"1",
    "Pclass":1,
    "Sex":"female",
    "Age":32,
    "Fare":76.2917
  },
  {
    "PassengerId":873,
    "Survived":"0",
    "Pclass":1,
    "Sex":"male",
    "Age":33,
    "Fare":5
  },
  {
    "PassengerId":810,
    "Survived":"1",
    "Pclass":1,
    "Sex":"female",
    "Age":33,
    "Fare":53.1
  },
  {
    "PassengerId":760,
    "Survived":"1",
    "Pclass":1,
    "Sex":"female",
    "Age":33,
    "Fare":86.5
  },
  {
    "PassengerId":413,
    "Survived":"1",
    "Pclass":1,
    "Sex":"female",
    "Age":33,
    "Fare":90
  },
  {
    "PassengerId":448,
    "Survived":"1",
    "Pclass":1,
    "Sex":"male",
    "Age":34,
    "Fare":26.55
  },
  {
    "PassengerId":702,
    "Survived":"1",
    "Pclass":1,
    "Sex":"male",
    "Age":35,
    "Fare":26.2875
  },
  {
    "PassengerId":605,
    "Survived":"1",
    "Pclass":1,
    "Sex":"male",
    "Age":35,
    "Fare":26.55
  },
  {
    "PassengerId":384,
    "Survived":"1",
    "Pclass":1,
    "Sex":"female",
    "Age":35,
    "Fare":52
  },
  {
    "PassengerId":4,
    "Survived":"1",
    "Pclass":1,
    "Sex":"female",
    "Age":35,
    "Fare":53.1
  },
  {
    "PassengerId":231,
    "Survived":"1",
    "Pclass":1,
    "Sex":"female",
    "Age":35,
    "Fare":83.475
  },
  {
    "PassengerId":487,
    "Survived":"1",
    "Pclass":1,
    "Sex":"female",
    "Age":35,
    "Fare":90
  },
  {
    "PassengerId":270,
    "Survived":"1",
    "Pclass":1,
    "Sex":"female",
    "Age":35,
    "Fare":135.6333
  },
  {
    "PassengerId":259,
    "Survived":"1",
    "Pclass":1,
    "Sex":"female",
    "Age":35,
    "Fare":275.3292
  },
  {
    "PassengerId":738,
    "Survived":"1",
    "Pclass":1,
    "Sex":"male",
    "Age":35,
    "Fare":275.3292
  },
  {
    "PassengerId":513,
    "Survived":"1",
    "Pclass":1,
    "Sex":"male",
    "Age":36,
    "Fare":26.2875
  },
  {
    "PassengerId":573,
    "Survived":"1",
    "Pclass":1,
    "Sex":"male",
    "Age":36,
    "Fare":26.3875
  },
  {
    "PassengerId":584,
    "Survived":"0",
    "Pclass":1,
    "Sex":"male",
    "Age":36,
    "Fare":40.125
  },
  {
    "PassengerId":541,
    "Survived":"1",
    "Pclass":1,
    "Sex":"female",
    "Age":36,
    "Fare":71
  },
  {
    "PassengerId":742,
    "Survived":"0",
    "Pclass":1,
    "Sex":"male",
    "Age":36,
    "Fare":78.85
  },
  {
    "PassengerId":391,
    "Survived":"1",
    "Pclass":1,
    "Sex":"male",
    "Age":36,
    "Fare":120
  },
  {
    "PassengerId":764,
    "Survived":"1",
    "Pclass":1,
    "Sex":"female",
    "Age":36,
    "Fare":120
  },
  {
    "PassengerId":326,
    "Survived":"1",
    "Pclass":1,
    "Sex":"female",
    "Age":36,
    "Fare":135.6333
  },
  {
    "PassengerId":680,
    "Survived":"1",
    "Pclass":1,
    "Sex":"male",
    "Age":36,
    "Fare":275.3292
  },
  {
    "PassengerId":274,
    "Survived":"0",
    "Pclass":1,
    "Sex":"male",
    "Age":37,
    "Fare":29.7
  },
  {
    "PassengerId":249,
    "Survived":"1",
    "Pclass":1,
    "Sex":"male",
    "Age":37,
    "Fare":52.5542
  },
  {
    "PassengerId":138,
    "Survived":"0",
    "Pclass":1,
    "Sex":"male",
    "Age":37,
    "Fare":53.1
  },
  {
    "PassengerId":823,
    "Survived":"0",
    "Pclass":1,
    "Sex":"male",
    "Age":38,
    "Fare":0
  },
  {
    "PassengerId":2,
    "Survived":"1",
    "Pclass":1,
    "Sex":"female",
    "Age":38,
    "Fare":71.2833
  },
  {
    "PassengerId":62,
    "Survived":"1",
    "Pclass":1,
    "Sex":"female",
    "Age":38,
    "Fare":80
  },
  {
    "PassengerId":225,
    "Survived":"1",
    "Pclass":1,
    "Sex":"male",
    "Age":38,
    "Fare":90
  },
  {
    "PassengerId":333,
    "Survived":"0",
    "Pclass":1,
    "Sex":"male",
    "Age":38,
    "Fare":153.4625
  },
  {
    "PassengerId":717,
    "Survived":"1",
    "Pclass":1,
    "Sex":"female",
    "Age":38,
    "Fare":227.525
  },
  {
    "PassengerId":807,
    "Survived":"0",
    "Pclass":1,
    "Sex":"male",
    "Age":39,
    "Fare":0
  },
  {
    "PassengerId":578,
    "Survived":"1",
    "Pclass":1,
    "Sex":"female",
    "Age":39,
    "Fare":55.9
  },
  {
    "PassengerId":559,
    "Survived":"1",
    "Pclass":1,
    "Sex":"female",
    "Age":39,
    "Fare":79.65
  },
  {
    "PassengerId":836,
    "Survived":"1",
    "Pclass":1,
    "Sex":"female",
    "Age":39,
    "Fare":83.1583
  },
  {
    "PassengerId":582,
    "Survived":"1",
    "Pclass":1,
    "Sex":"female",
    "Age":39,
    "Fare":110.8833
  },
  {
    "PassengerId":264,
    "Survived":"0",
    "Pclass":1,
    "Sex":"male",
    "Age":40,
    "Fare":0
  },
  {
    "PassengerId":31,
    "Survived":"0",
    "Pclass":1,
    "Sex":"male",
    "Age":40,
    "Fare":27.7208
  },
  {
    "PassengerId":210,
    "Survived":"1",
    "Pclass":1,
    "Sex":"male",
    "Age":40,
    "Fare":31
  },
  {
    "PassengerId":320,
    "Survived":"1",
    "Pclass":1,
    "Sex":"female",
    "Age":40,
    "Fare":134.5
  },
  {
    "PassengerId":610,
    "Survived":"1",
    "Pclass":1,
    "Sex":"female",
    "Age":40,
    "Fare":153.4625
  },
  {
    "PassengerId":338,
    "Survived":"1",
    "Pclass":1,
    "Sex":"female",
    "Age":41,
    "Fare":134.5
  },
  {
    "PassengerId":708,
    "Survived":"1",
    "Pclass":1,
    "Sex":"male",
    "Age":42,
    "Fare":26.2875
  },
  {
    "PassengerId":36,
    "Survived":"0",
    "Pclass":1,
    "Sex":"male",
    "Age":42,
    "Fare":52
  },
  {
    "PassengerId":622,
    "Survived":"1",
    "Pclass":1,
    "Sex":"male",
    "Age":42,
    "Fare":52.5542
  },
  {
    "PassengerId":381,
    "Survived":"1",
    "Pclass":1,
    "Sex":"female",
    "Age":42,
    "Fare":227.525
  },
  {
    "PassengerId":780,
    "Survived":"1",
    "Pclass":1,
    "Sex":"female",
    "Age":43,
    "Fare":211.3375
  },
  {
    "PassengerId":195,
    "Survived":"1",
    "Pclass":1,
    "Sex":"female",
    "Age":44,
    "Fare":27.7208
  },
  {
    "PassengerId":524,
    "Survived":"1",
    "Pclass":1,
    "Sex":"female",
    "Age":44,
    "Fare":57.9792
  },
  {
    "PassengerId":246,
    "Survived":"0",
    "Pclass":1,
    "Sex":"male",
    "Age":44,
    "Fare":90
  },
  {
    "PassengerId":537,
    "Survived":"0",
    "Pclass":1,
    "Sex":"male",
    "Age":45,
    "Fare":26.55
  },
  {
    "PassengerId":188,
    "Survived":"1",
    "Pclass":1,
    "Sex":"male",
    "Age":45,
    "Fare":26.55
  },
  {
    "PassengerId":340,
    "Survived":"0",
    "Pclass":1,
    "Sex":"male",
    "Age":45,
    "Fare":35.5
  },
  {
    "PassengerId":63,
    "Survived":"0",
    "Pclass":1,
    "Sex":"male",
    "Age":45,
    "Fare":83.475
  },
  {
    "PassengerId":857,
    "Survived":"1",
    "Pclass":1,
    "Sex":"female",
    "Age":45,
    "Fare":164.8667
  },
  {
    "PassengerId":332,
    "Survived":"0",
    "Pclass":1,
    "Sex":"male",
    "Age":45.5,
    "Fare":28.5
  },
  {
    "PassengerId":93,
    "Survived":"0",
    "Pclass":1,
    "Sex":"male",
    "Age":46,
    "Fare":61.175
  },
  {
    "PassengerId":790,
    "Survived":"0",
    "Pclass":1,
    "Sex":"male",
    "Age":46,
    "Fare":79.2
  },
  {
    "PassengerId":663,
    "Survived":"0",
    "Pclass":1,
    "Sex":"male",
    "Age":47,
    "Fare":25.5875
  },
  {
    "PassengerId":516,
    "Survived":"0",
    "Pclass":1,
    "Sex":"male",
    "Age":47,
    "Fare":34.0208
  },
  {
    "PassengerId":463,
    "Survived":"0",
    "Pclass":1,
    "Sex":"male",
    "Age":47,
    "Fare":38.5
  },
  {
    "PassengerId":111,
    "Survived":"0",
    "Pclass":1,
    "Sex":"male",
    "Age":47,
    "Fare":52
  },
  {
    "PassengerId":872,
    "Survived":"1",
    "Pclass":1,
    "Sex":"female",
    "Age":47,
    "Fare":52.5542
  },
  {
    "PassengerId":863,
    "Survived":"1",
    "Pclass":1,
    "Sex":"female",
    "Age":48,
    "Fare":25.9292
  },
  {
    "PassengerId":461,
    "Survived":"1",
    "Pclass":1,
    "Sex":"male",
    "Age":48,
    "Fare":26.55
  },
  {
    "PassengerId":557,
    "Survived":"1",
    "Pclass":1,
    "Sex":"female",
    "Age":48,
    "Fare":39.6
  },
  {
    "PassengerId":713,
    "Survived":"1",
    "Pclass":1,
    "Sex":"male",
    "Age":48,
    "Fare":52
  },
  {
    "PassengerId":646,
    "Survived":"1",
    "Pclass":1,
    "Sex":"male",
    "Age":48,
    "Fare":76.7292
  },
  {
    "PassengerId":797,
    "Survived":"1",
    "Pclass":1,
    "Sex":"female",
    "Age":49,
    "Fare":25.9292
  },
  {
    "PassengerId":600,
    "Survived":"1",
    "Pclass":1,
    "Sex":"male",
    "Age":49,
    "Fare":56.9292
  },
  {
    "PassengerId":53,
    "Survived":"1",
    "Pclass":1,
    "Sex":"female",
    "Age":49,
    "Fare":76.7292
  },
  {
    "PassengerId":454,
    "Survived":"1",
    "Pclass":1,
    "Sex":"male",
    "Age":49,
    "Fare":89.1042
  },
  {
    "PassengerId":699,
    "Survived":"0",
    "Pclass":1,
    "Sex":"male",
    "Age":49,
    "Fare":110.8833
  },
  {
    "PassengerId":178,
    "Survived":"0",
    "Pclass":1,
    "Sex":"female",
    "Age":50,
    "Fare":28.7125
  },
  {
    "PassengerId":435,
    "Survived":"0",
    "Pclass":1,
    "Sex":"male",
    "Age":50,
    "Fare":55.9
  },
  {
    "PassengerId":545,
    "Survived":"0",
    "Pclass":1,
    "Sex":"male",
    "Age":50,
    "Fare":106.425
  },
  {
    "PassengerId":661,
    "Survived":"1",
    "Pclass":1,
    "Sex":"male",
    "Age":50,
    "Fare":133.65
  },
  {
    "PassengerId":300,
    "Survived":"1",
    "Pclass":1,
    "Sex":"female",
    "Age":50,
    "Fare":247.5208
  },
  {
    "PassengerId":858,
    "Survived":"1",
    "Pclass":1,
    "Sex":"male",
    "Age":51,
    "Fare":26.55
  },
  {
    "PassengerId":156,
    "Survived":"0",
    "Pclass":1,
    "Sex":"male",
    "Age":51,
    "Fare":61.3792
  },
  {
    "PassengerId":766,
    "Survived":"1",
    "Pclass":1,
    "Sex":"female",
    "Age":51,
    "Fare":77.9583
  },
  {
    "PassengerId":450,
    "Survived":"1",
    "Pclass":1,
    "Sex":"male",
    "Age":52,
    "Fare":30.5
  },
  {
    "PassengerId":592,
    "Survived":"1",
    "Pclass":1,
    "Sex":"female",
    "Age":52,
    "Fare":78.2667
  },
  {
    "PassengerId":263,
    "Survived":"0",
    "Pclass":1,
    "Sex":"male",
    "Age":52,
    "Fare":79.65
  },
  {
    "PassengerId":821,
    "Survived":"1",
    "Pclass":1,
    "Sex":"female",
    "Age":52,
    "Fare":93.5
  },
  {
    "PassengerId":572,
    "Survived":"1",
    "Pclass":1,
    "Sex":"female",
    "Age":53,
    "Fare":51.4792
  },
  {
    "PassengerId":7,
    "Survived":"0",
    "Pclass":1,
    "Sex":"male",
    "Age":54,
    "Fare":51.8625
  },
  {
    "PassengerId":514,
    "Survived":"1",
    "Pclass":1,
    "Sex":"female",
    "Age":54,
    "Fare":59.4
  },
  {
    "PassengerId":125,
    "Survived":"0",
    "Pclass":1,
    "Sex":"male",
    "Age":54,
    "Fare":77.2875
  },
  {
    "PassengerId":497,
    "Survived":"1",
    "Pclass":1,
    "Sex":"female",
    "Age":54,
    "Fare":78.2667
  },
  {
    "PassengerId":493,
    "Survived":"0",
    "Pclass":1,
    "Sex":"male",
    "Age":55,
    "Fare":30.5
  },
  {
    "PassengerId":468,
    "Survived":"0",
    "Pclass":1,
    "Sex":"male",
    "Age":56,
    "Fare":26.55
  },
  {
    "PassengerId":175,
    "Survived":"0",
    "Pclass":1,
    "Sex":"male",
    "Age":56,
    "Fare":30.6958
  },
  {
    "PassengerId":648,
    "Survived":"1",
    "Pclass":1,
    "Sex":"male",
    "Age":56,
    "Fare":35.5
  },
  {
    "PassengerId":880,
    "Survived":"1",
    "Pclass":1,
    "Sex":"female",
    "Age":56,
    "Fare":83.1583
  },
  {
    "PassengerId":12,
    "Survived":"1",
    "Pclass":1,
    "Sex":"female",
    "Age":58,
    "Fare":26.55
  },
  {
    "PassengerId":488,
    "Survived":"0",
    "Pclass":1,
    "Sex":"male",
    "Age":58,
    "Fare":29.7
  },
  {
    "PassengerId":660,
    "Survived":"0",
    "Pclass":1,
    "Sex":"male",
    "Age":58,
    "Fare":113.275
  },
  {
    "PassengerId":196,
    "Survived":"1",
    "Pclass":1,
    "Sex":"female",
    "Age":58,
    "Fare":146.5208
  },
  {
    "PassengerId":269,
    "Survived":"1",
    "Pclass":1,
    "Sex":"female",
    "Age":58,
    "Fare":153.4625
  },
  {
    "PassengerId":695,
    "Survived":"0",
    "Pclass":1,
    "Sex":"male",
    "Age":60,
    "Fare":26.55
  },
  {
    "PassengerId":367,
    "Survived":"1",
    "Pclass":1,
    "Sex":"female",
    "Age":60,
    "Fare":75.25
  },
  {
    "PassengerId":588,
    "Survived":"1",
    "Pclass":1,
    "Sex":"male",
    "Age":60,
    "Fare":79.2
  },
  {
    "PassengerId":626,
    "Survived":"0",
    "Pclass":1,
    "Sex":"male",
    "Age":61,
    "Fare":32.3208
  },
  {
    "PassengerId":171,
    "Survived":"0",
    "Pclass":1,
    "Sex":"male",
    "Age":61,
    "Fare":33.5
  },
  {
    "PassengerId":253,
    "Survived":"0",
    "Pclass":1,
    "Sex":"male",
    "Age":62,
    "Fare":26.55
  },
  {
    "PassengerId":556,
    "Survived":"0",
    "Pclass":1,
    "Sex":"male",
    "Age":62,
    "Fare":26.55
  },
  {
    "PassengerId":830,
    "Survived":"1",
    "Pclass":1,
    "Sex":"female",
    "Age":62,
    "Fare":80
  },
  {
    "PassengerId":276,
    "Survived":"1",
    "Pclass":1,
    "Sex":"female",
    "Age":63,
    "Fare":77.9583
  },
  {
    "PassengerId":546,
    "Survived":"0",
    "Pclass":1,
    "Sex":"male",
    "Age":64,
    "Fare":26
  },
  {
    "PassengerId":439,
    "Survived":"0",
    "Pclass":1,
    "Sex":"male",
    "Age":64,
    "Fare":263
  },
  {
    "PassengerId":457,
    "Survived":"0",
    "Pclass":1,
    "Sex":"male",
    "Age":65,
    "Fare":26.55
  },
  {
    "PassengerId":55,
    "Survived":"0",
    "Pclass":1,
    "Sex":"male",
    "Age":65,
    "Fare":61.9792
  },
  {
    "PassengerId":746,
    "Survived":"0",
    "Pclass":1,
    "Sex":"male",
    "Age":70,
    "Fare":71
  },
  {
    "PassengerId":97,
    "Survived":"0",
    "Pclass":1,
    "Sex":"male",
    "Age":71,
    "Fare":34.6542
  },
  {
    "PassengerId":494,
    "Survived":"0",
    "Pclass":1,
    "Sex":"male",
    "Age":71,
    "Fare":49.5042
  },
  {
    "PassengerId":631,
    "Survived":"1",
    "Pclass":1,
    "Sex":"male",
    "Age":80,
    "Fare":30
  },
  {
    "PassengerId":756,
    "Survived":"1",
    "Pclass":2,
    "Sex":"male",
    "Age":0.67,
    "Fare":14.5
  },
  {
    "PassengerId":832,
    "Survived":"1",
    "Pclass":2,
    "Sex":"male",
    "Age":0.83,
    "Fare":18.75
  },
  {
    "PassengerId":79,
    "Survived":"1",
    "Pclass":2,
    "Sex":"male",
    "Age":0.83,
    "Fare":29
  },
  {
    "PassengerId":828,
    "Survived":"1",
    "Pclass":2,
    "Sex":"male",
    "Age":1,
    "Fare":37.0042
  },
  {
    "PassengerId":184,
    "Survived":"1",
    "Pclass":2,
    "Sex":"male",
    "Age":1,
    "Fare":39
  },
  {
    "PassengerId":341,
    "Survived":"1",
    "Pclass":2,
    "Sex":"male",
    "Age":2,
    "Fare":26
  },
  {
    "PassengerId":531,
    "Survived":"1",
    "Pclass":2,
    "Sex":"female",
    "Age":2,
    "Fare":26
  },
  {
    "PassengerId":408,
    "Survived":"1",
    "Pclass":2,
    "Sex":"male",
    "Age":3,
    "Fare":18.75
  },
  {
    "PassengerId":194,
    "Survived":"1",
    "Pclass":2,
    "Sex":"male",
    "Age":3,
    "Fare":26
  },
  {
    "PassengerId":44,
    "Survived":"1",
    "Pclass":2,
    "Sex":"female",
    "Age":3,
    "Fare":41.5792
  },
  {
    "PassengerId":751,
    "Survived":"1",
    "Pclass":2,
    "Sex":"female",
    "Age":4,
    "Fare":23
  },
  {
    "PassengerId":619,
    "Survived":"1",
    "Pclass":2,
    "Sex":"female",
    "Age":4,
    "Fare":39
  },
  {
    "PassengerId":59,
    "Survived":"1",
    "Pclass":2,
    "Sex":"female",
    "Age":5,
    "Fare":27.75
  },
  {
    "PassengerId":721,
    "Survived":"1",
    "Pclass":2,
    "Sex":"female",
    "Age":6,
    "Fare":33
  },
  {
    "PassengerId":536,
    "Survived":"1",
    "Pclass":2,
    "Sex":"female",
    "Age":7,
    "Fare":26.25
  },
  {
    "PassengerId":238,
    "Survived":"1",
    "Pclass":2,
    "Sex":"female",
    "Age":8,
    "Fare":26.25
  },
  {
    "PassengerId":550,
    "Survived":"1",
    "Pclass":2,
    "Sex":"male",
    "Age":8,
    "Fare":36.75
  },
  {
    "PassengerId":447,
    "Survived":"1",
    "Pclass":2,
    "Sex":"female",
    "Age":13,
    "Fare":19.5
  },
  {
    "PassengerId":10,
    "Survived":"1",
    "Pclass":2,
    "Sex":"female",
    "Age":14,
    "Fare":30.0708
  },
  {
    "PassengerId":842,
    "Survived":"0",
    "Pclass":2,
    "Sex":"male",
    "Age":16,
    "Fare":10.5
  },
  {
    "PassengerId":792,
    "Survived":"0",
    "Pclass":2,
    "Sex":"male",
    "Age":16,
    "Fare":26
  },
  {
    "PassengerId":85,
    "Survived":"1",
    "Pclass":2,
    "Sex":"female",
    "Age":17,
    "Fare":10.5
  },
  {
    "PassengerId":390,
    "Survived":"1",
    "Pclass":2,
    "Sex":"female",
    "Age":17,
    "Fare":12
  },
  {
    "PassengerId":758,
    "Survived":"0",
    "Pclass":2,
    "Sex":"male",
    "Age":18,
    "Fare":11.5
  },
  {
    "PassengerId":145,
    "Survived":"0",
    "Pclass":2,
    "Sex":"male",
    "Age":18,
    "Fare":11.5
  },
  {
    "PassengerId":229,
    "Survived":"0",
    "Pclass":2,
    "Sex":"male",
    "Age":18,
    "Fare":13
  },
  {
    "PassengerId":418,
    "Survived":"1",
    "Pclass":2,
    "Sex":"female",
    "Age":18,
    "Fare":13
  },
  {
    "PassengerId":652,
    "Survived":"1",
    "Pclass":2,
    "Sex":"female",
    "Age":18,
    "Fare":23
  },
  {
    "PassengerId":386,
    "Survived":"0",
    "Pclass":2,
    "Sex":"male",
    "Age":18,
    "Fare":73.5
  },
  {
    "PassengerId":239,
    "Survived":"0",
    "Pclass":2,
    "Sex":"male",
    "Age":19,
    "Fare":10.5
  },
  {
    "PassengerId":227,
    "Survived":"1",
    "Pclass":2,
    "Sex":"male",
    "Age":19,
    "Fare":10.5
  },
  {
    "PassengerId":192,
    "Survived":"0",
    "Pclass":2,
    "Sex":"male",
    "Age":19,
    "Fare":13
  },
  {
    "PassengerId":547,
    "Survived":"1",
    "Pclass":2,
    "Sex":"female",
    "Age":19,
    "Fare":26
  },
  {
    "PassengerId":428,
    "Survived":"1",
    "Pclass":2,
    "Sex":"female",
    "Age":19,
    "Fare":26
  },
  {
    "PassengerId":146,
    "Survived":"0",
    "Pclass":2,
    "Sex":"male",
    "Age":19,
    "Fare":36.75
  },
  {
    "PassengerId":57,
    "Survived":"1",
    "Pclass":2,
    "Sex":"female",
    "Age":21,
    "Fare":10.5
  },
  {
    "PassengerId":862,
    "Survived":"0",
    "Pclass":2,
    "Sex":"male",
    "Age":21,
    "Fare":11.5
  },
  {
    "PassengerId":121,
    "Survived":"0",
    "Pclass":2,
    "Sex":"male",
    "Age":21,
    "Fare":73.5
  },
  {
    "PassengerId":73,
    "Survived":"0",
    "Pclass":2,
    "Sex":"male",
    "Age":21,
    "Fare":73.5
  },
  {
    "PassengerId":324,
    "Survived":"1",
    "Pclass":2,
    "Sex":"female",
    "Age":22,
    "Fare":29
  },
  {
    "PassengerId":609,
    "Survived":"1",
    "Pclass":2,
    "Sex":"female",
    "Age":22,
    "Fare":41.5792
  },
  {
    "PassengerId":399,
    "Survived":"0",
    "Pclass":2,
    "Sex":"male",
    "Age":23,
    "Fare":10.5
  },
  {
    "PassengerId":530,
    "Survived":"0",
    "Pclass":2,
    "Sex":"male",
    "Age":23,
    "Fare":11.5
  },
  {
    "PassengerId":735,
    "Survived":"0",
    "Pclass":2,
    "Sex":"male",
    "Age":23,
    "Fare":13
  },
  {
    "PassengerId":734,
    "Survived":"0",
    "Pclass":2,
    "Sex":"male",
    "Age":23,
    "Fare":13
  },
  {
    "PassengerId":659,
    "Survived":"0",
    "Pclass":2,
    "Sex":"male",
    "Age":23,
    "Fare":13
  },
  {
    "PassengerId":474,
    "Survived":"1",
    "Pclass":2,
    "Sex":"female",
    "Age":23,
    "Fare":13.7917
  },
  {
    "PassengerId":136,
    "Survived":"0",
    "Pclass":2,
    "Sex":"male",
    "Age":23,
    "Fare":15.0458
  },
  {
    "PassengerId":235,
    "Survived":"0",
    "Pclass":2,
    "Sex":"male",
    "Age":24,
    "Fare":10.5
  },
  {
    "PassengerId":865,
    "Survived":"0",
    "Pclass":2,
    "Sex":"male",
    "Age":24,
    "Fare":13
  },
  {
    "PassengerId":346,
    "Survived":"1",
    "Pclass":2,
    "Sex":"female",
    "Age":24,
    "Fare":13
  },
  {
    "PassengerId":200,
    "Survived":"0",
    "Pclass":2,
    "Sex":"female",
    "Age":24,
    "Fare":13
  },
  {
    "PassengerId":248,
    "Survived":"1",
    "Pclass":2,
    "Sex":"female",
    "Age":24,
    "Fare":14.5
  },
  {
    "PassengerId":438,
    "Survived":"1",
    "Pclass":2,
    "Sex":"female",
    "Age":24,
    "Fare":18.75
  },
  {
    "PassengerId":317,
    "Survived":"1",
    "Pclass":2,
    "Sex":"female",
    "Age":24,
    "Fare":26
  },
  {
    "PassengerId":601,
    "Survived":"1",
    "Pclass":2,
    "Sex":"female",
    "Age":24,
    "Fare":27
  },
  {
    "PassengerId":616,
    "Survived":"1",
    "Pclass":2,
    "Sex":"female",
    "Age":24,
    "Fare":65
  },
  {
    "PassengerId":656,
    "Survived":"0",
    "Pclass":2,
    "Sex":"male",
    "Age":24,
    "Fare":73.5
  },
  {
    "PassengerId":667,
    "Survived":"0",
    "Pclass":2,
    "Sex":"male",
    "Age":25,
    "Fare":13
  },
  {
    "PassengerId":344,
    "Survived":"0",
    "Pclass":2,
    "Sex":"male",
    "Age":25,
    "Fare":13
  },
  {
    "PassengerId":135,
    "Survived":"0",
    "Pclass":2,
    "Sex":"male",
    "Age":25,
    "Fare":13
  },
  {
    "PassengerId":881,
    "Survived":"1",
    "Pclass":2,
    "Sex":"female",
    "Age":25,
    "Fare":26
  },
  {
    "PassengerId":729,
    "Survived":"0",
    "Pclass":2,
    "Sex":"male",
    "Age":25,
    "Fare":26
  },
  {
    "PassengerId":581,
    "Survived":"1",
    "Pclass":2,
    "Sex":"female",
    "Age":25,
    "Fare":30
  },
  {
    "PassengerId":686,
    "Survived":"0",
    "Pclass":2,
    "Sex":"male",
    "Age":25,
    "Fare":41.5792
  },
  {
    "PassengerId":620,
    "Survived":"0",
    "Pclass":2,
    "Sex":"male",
    "Age":26,
    "Fare":10.5
  },
  {
    "PassengerId":313,
    "Survived":"0",
    "Pclass":2,
    "Sex":"female",
    "Age":26,
    "Fare":26
  },
  {
    "PassengerId":718,
    "Survived":"1",
    "Pclass":2,
    "Sex":"female",
    "Age":27,
    "Fare":10.5
  },
  {
    "PassengerId":887,
    "Survived":"0",
    "Pclass":2,
    "Sex":"male",
    "Age":27,
    "Fare":13
  },
  {
    "PassengerId":222,
    "Survived":"0",
    "Pclass":2,
    "Sex":"male",
    "Age":27,
    "Fare":13
  },
  {
    "PassengerId":867,
    "Survived":"1",
    "Pclass":2,
    "Sex":"female",
    "Age":27,
    "Fare":13.8583
  },
  {
    "PassengerId":42,
    "Survived":"0",
    "Pclass":2,
    "Sex":"female",
    "Age":27,
    "Fare":21
  },
  {
    "PassengerId":552,
    "Survived":"0",
    "Pclass":2,
    "Sex":"male",
    "Age":27,
    "Fare":26
  },
  {
    "PassengerId":884,
    "Survived":"0",
    "Pclass":2,
    "Sex":"male",
    "Age":28,
    "Fare":10.5
  },
  {
    "PassengerId":400,
    "Survived":"1",
    "Pclass":2,
    "Sex":"female",
    "Age":28,
    "Fare":12.65
  },
  {
    "PassengerId":444,
    "Survived":"1",
    "Pclass":2,
    "Sex":"female",
    "Age":28,
    "Fare":13
  },
  {
    "PassengerId":636,
    "Survived":"1",
    "Pclass":2,
    "Sex":"female",
    "Age":28,
    "Fare":13
  },
  {
    "PassengerId":343,
    "Survived":"0",
    "Pclass":2,
    "Sex":"male",
    "Age":28,
    "Fare":13
  },
  {
    "PassengerId":563,
    "Survived":"0",
    "Pclass":2,
    "Sex":"male",
    "Age":28,
    "Fare":13.5
  },
  {
    "PassengerId":875,
    "Survived":"1",
    "Pclass":2,
    "Sex":"female",
    "Age":28,
    "Fare":24
  },
  {
    "PassengerId":427,
    "Survived":"1",
    "Pclass":2,
    "Sex":"female",
    "Age":28,
    "Fare":26
  },
  {
    "PassengerId":849,
    "Survived":"0",
    "Pclass":2,
    "Sex":"male",
    "Age":28,
    "Fare":33
  },
  {
    "PassengerId":67,
    "Survived":"1",
    "Pclass":2,
    "Sex":"female",
    "Age":29,
    "Fare":10.5
  },
  {
    "PassengerId":243,
    "Survived":"0",
    "Pclass":2,
    "Sex":"male",
    "Age":29,
    "Fare":10.5
  },
  {
    "PassengerId":118,
    "Survived":"0",
    "Pclass":2,
    "Sex":"male",
    "Age":29,
    "Fare":21
  },
  {
    "PassengerId":54,
    "Survived":"1",
    "Pclass":2,
    "Sex":"female",
    "Age":29,
    "Fare":26
  },
  {
    "PassengerId":134,
    "Survived":"1",
    "Pclass":2,
    "Sex":"female",
    "Age":29,
    "Fare":26
  },
  {
    "PassengerId":362,
    "Survived":"0",
    "Pclass":2,
    "Sex":"male",
    "Age":29,
    "Fare":27.7208
  },
  {
    "PassengerId":220,
    "Survived":"0",
    "Pclass":2,
    "Sex":"male",
    "Age":30,
    "Fare":10.5
  },
  {
    "PassengerId":323,
    "Survived":"1",
    "Pclass":2,
    "Sex":"female",
    "Age":30,
    "Fare":12.35
  },
  {
    "PassengerId":179,
    "Survived":"0",
    "Pclass":2,
    "Sex":"male",
    "Age":30,
    "Fare":13
  },
  {
    "PassengerId":419,
    "Survived":"0",
    "Pclass":2,
    "Sex":"male",
    "Age":30,
    "Fare":13
  },
  {
    "PassengerId":748,
    "Survived":"1",
    "Pclass":2,
    "Sex":"female",
    "Age":30,
    "Fare":13
  },
  {
    "PassengerId":214,
    "Survived":"0",
    "Pclass":2,
    "Sex":"male",
    "Age":30,
    "Fare":13
  },
  {
    "PassengerId":727,
    "Survived":"1",
    "Pclass":2,
    "Sex":"female",
    "Age":30,
    "Fare":21
  },
  {
    "PassengerId":309,
    "Survived":"0",
    "Pclass":2,
    "Sex":"male",
    "Age":30,
    "Fare":24
  },
  {
    "PassengerId":440,
    "Survived":"0",
    "Pclass":2,
    "Sex":"male",
    "Age":31,
    "Fare":10.5
  },
  {
    "PassengerId":674,
    "Survived":"1",
    "Pclass":2,
    "Sex":"male",
    "Age":31,
    "Fare":13
  },
  {
    "PassengerId":802,
    "Survived":"1",
    "Pclass":2,
    "Sex":"female",
    "Age":31,
    "Fare":26.25
  },
  {
    "PassengerId":638,
    "Survived":"0",
    "Pclass":2,
    "Sex":"male",
    "Age":31,
    "Fare":26.25
  },
  {
    "PassengerId":818,
    "Survived":"0",
    "Pclass":2,
    "Sex":"male",
    "Age":31,
    "Fare":37.0042
  },
  {
    "PassengerId":71,
    "Survived":"0",
    "Pclass":2,
    "Sex":"male",
    "Age":32,
    "Fare":10.5
  },
  {
    "PassengerId":191,
    "Survived":"1",
    "Pclass":2,
    "Sex":"female",
    "Age":32,
    "Fare":13
  },
  {
    "PassengerId":544,
    "Survived":"1",
    "Pclass":2,
    "Sex":"male",
    "Age":32,
    "Fare":26
  },
  {
    "PassengerId":666,
    "Survived":"0",
    "Pclass":2,
    "Sex":"male",
    "Age":32,
    "Fare":73.5
  },
  {
    "PassengerId":124,
    "Survived":"1",
    "Pclass":2,
    "Sex":"female",
    "Age":32.5,
    "Fare":13
  },
  {
    "PassengerId":123,
    "Survived":"0",
    "Pclass":2,
    "Sex":"male",
    "Age":32.5,
    "Fare":30.0708
  },
  {
    "PassengerId":240,
    "Survived":"0",
    "Pclass":2,
    "Sex":"male",
    "Age":33,
    "Fare":12.275
  },
  {
    "PassengerId":507,
    "Survived":"1",
    "Pclass":2,
    "Sex":"female",
    "Age":33,
    "Fare":26
  },
  {
    "PassengerId":473,
    "Survived":"1",
    "Pclass":2,
    "Sex":"female",
    "Age":33,
    "Fare":27.75
  },
  {
    "PassengerId":517,
    "Survived":"1",
    "Pclass":2,
    "Sex":"female",
    "Age":34,
    "Fare":10.5
  },
  {
    "PassengerId":723,
    "Survived":"0",
    "Pclass":2,
    "Sex":"male",
    "Age":34,
    "Fare":13
  },
  {
    "PassengerId":801,
    "Survived":"0",
    "Pclass":2,
    "Sex":"male",
    "Age":34,
    "Fare":13
  },
  {
    "PassengerId":577,
    "Survived":"1",
    "Pclass":2,
    "Sex":"female",
    "Age":34,
    "Fare":13
  },
  {
    "PassengerId":22,
    "Survived":"1",
    "Pclass":2,
    "Sex":"male",
    "Age":34,
    "Fare":13
  },
  {
    "PassengerId":406,
    "Survived":"0",
    "Pclass":2,
    "Sex":"male",
    "Age":34,
    "Fare":21
  },
  {
    "PassengerId":477,
    "Survived":"0",
    "Pclass":2,
    "Sex":"male",
    "Age":34,
    "Fare":21
  },
  {
    "PassengerId":99,
    "Survived":"1",
    "Pclass":2,
    "Sex":"female",
    "Age":34,
    "Fare":23
  },
  {
    "PassengerId":100,
    "Survived":"0",
    "Pclass":2,
    "Sex":"male",
    "Age":34,
    "Fare":26
  },
  {
    "PassengerId":417,
    "Survived":"1",
    "Pclass":2,
    "Sex":"female",
    "Age":34,
    "Fare":32.5
  },
  {
    "PassengerId":813,
    "Survived":"0",
    "Pclass":2,
    "Sex":"male",
    "Age":35,
    "Fare":10.5
  },
  {
    "PassengerId":212,
    "Survived":"1",
    "Pclass":2,
    "Sex":"female",
    "Age":35,
    "Fare":21
  },
  {
    "PassengerId":21,
    "Survived":"0",
    "Pclass":2,
    "Sex":"male",
    "Age":35,
    "Fare":26
  },
  {
    "PassengerId":266,
    "Survived":"0",
    "Pclass":2,
    "Sex":"male",
    "Age":36,
    "Fare":10.5
  },
  {
    "PassengerId":293,
    "Survived":"0",
    "Pclass":2,
    "Sex":"male",
    "Age":36,
    "Fare":12.875
  },
  {
    "PassengerId":328,
    "Survived":"1",
    "Pclass":2,
    "Sex":"female",
    "Age":36,
    "Fare":13
  },
  {
    "PassengerId":345,
    "Survived":"0",
    "Pclass":2,
    "Sex":"male",
    "Age":36,
    "Fare":13
  },
  {
    "PassengerId":388,
    "Survived":"1",
    "Pclass":2,
    "Sex":"female",
    "Age":36,
    "Fare":13
  },
  {
    "PassengerId":519,
    "Survived":"1",
    "Pclass":2,
    "Sex":"female",
    "Age":36,
    "Fare":26
  },
  {
    "PassengerId":451,
    "Survived":"0",
    "Pclass":2,
    "Sex":"male",
    "Age":36,
    "Fare":27.75
  },
  {
    "PassengerId":149,
    "Survived":"0",
    "Pclass":2,
    "Sex":"male",
    "Age":36.5,
    "Fare":26
  },
  {
    "PassengerId":595,
    "Survived":"0",
    "Pclass":2,
    "Sex":"male",
    "Age":37,
    "Fare":26
  },
  {
    "PassengerId":358,
    "Survived":"0",
    "Pclass":2,
    "Sex":"female",
    "Age":38,
    "Fare":13
  },
  {
    "PassengerId":796,
    "Survived":"0",
    "Pclass":2,
    "Sex":"male",
    "Age":39,
    "Fare":13
  },
  {
    "PassengerId":809,
    "Survived":"0",
    "Pclass":2,
    "Sex":"male",
    "Age":39,
    "Fare":13
  },
  {
    "PassengerId":706,
    "Survived":"0",
    "Pclass":2,
    "Sex":"male",
    "Age":39,
    "Fare":26
  },
  {
    "PassengerId":347,
    "Survived":"1",
    "Pclass":2,
    "Sex":"female",
    "Age":40,
    "Fare":13
  },
  {
    "PassengerId":162,
    "Survived":"1",
    "Pclass":2,
    "Sex":"female",
    "Age":40,
    "Fare":15.75
  },
  {
    "PassengerId":671,
    "Survived":"1",
    "Pclass":2,
    "Sex":"female",
    "Age":40,
    "Fare":39
  },
  {
    "PassengerId":273,
    "Survived":"1",
    "Pclass":2,
    "Sex":"female",
    "Age":41,
    "Fare":19.5
  },
  {
    "PassengerId":150,
    "Survived":"0",
    "Pclass":2,
    "Sex":"male",
    "Age":42,
    "Fare":13
  },
  {
    "PassengerId":289,
    "Survived":"1",
    "Pclass":2,
    "Sex":"male",
    "Age":42,
    "Fare":13
  },
  {
    "PassengerId":866,
    "Survived":"1",
    "Pclass":2,
    "Sex":"female",
    "Age":42,
    "Fare":13
  },
  {
    "PassengerId":433,
    "Survived":"1",
    "Pclass":2,
    "Sex":"female",
    "Age":42,
    "Fare":26
  },
  {
    "PassengerId":218,
    "Survived":"0",
    "Pclass":2,
    "Sex":"male",
    "Age":42,
    "Fare":27
  },
  {
    "PassengerId":315,
    "Survived":"0",
    "Pclass":2,
    "Sex":"male",
    "Age":43,
    "Fare":26.25
  },
  {
    "PassengerId":855,
    "Survived":"0",
    "Pclass":2,
    "Sex":"female",
    "Age":44,
    "Fare":26
  },
  {
    "PassengerId":237,
    "Survived":"0",
    "Pclass":2,
    "Sex":"male",
    "Age":44,
    "Fare":26
  },
  {
    "PassengerId":707,
    "Survived":"1",
    "Pclass":2,
    "Sex":"female",
    "Age":45,
    "Fare":13.5
  },
  {
    "PassengerId":441,
    "Survived":"1",
    "Pclass":2,
    "Sex":"female",
    "Age":45,
    "Fare":26.25
  },
  {
    "PassengerId":398,
    "Survived":"0",
    "Pclass":2,
    "Sex":"male",
    "Age":46,
    "Fare":26
  },
  {
    "PassengerId":587,
    "Survived":"0",
    "Pclass":2,
    "Sex":"male",
    "Age":47,
    "Fare":15
  },
  {
    "PassengerId":464,
    "Survived":"0",
    "Pclass":2,
    "Sex":"male",
    "Age":48,
    "Fare":13
  },
  {
    "PassengerId":755,
    "Survived":"1",
    "Pclass":2,
    "Sex":"female",
    "Age":48,
    "Fare":65
  },
  {
    "PassengerId":527,
    "Survived":"1",
    "Pclass":2,
    "Sex":"female",
    "Age":50,
    "Fare":10.5
  },
  {
    "PassengerId":459,
    "Survived":"1",
    "Pclass":2,
    "Sex":"female",
    "Age":50,
    "Fare":10.5
  },
  {
    "PassengerId":724,
    "Survived":"0",
    "Pclass":2,
    "Sex":"male",
    "Age":50,
    "Fare":13
  },
  {
    "PassengerId":260,
    "Survived":"1",
    "Pclass":2,
    "Sex":"female",
    "Age":50,
    "Fare":26
  },
  {
    "PassengerId":151,
    "Survived":"0",
    "Pclass":2,
    "Sex":"male",
    "Age":51,
    "Fare":12.525
  },
  {
    "PassengerId":715,
    "Survived":"0",
    "Pclass":2,
    "Sex":"male",
    "Age":52,
    "Fare":13
  },
  {
    "PassengerId":696,
    "Survived":"0",
    "Pclass":2,
    "Sex":"male",
    "Age":52,
    "Fare":13.5
  },
  {
    "PassengerId":318,
    "Survived":"0",
    "Pclass":2,
    "Sex":"male",
    "Age":54,
    "Fare":14
  },
  {
    "PassengerId":775,
    "Survived":"1",
    "Pclass":2,
    "Sex":"female",
    "Age":54,
    "Fare":23
  },
  {
    "PassengerId":250,
    "Survived":"0",
    "Pclass":2,
    "Sex":"male",
    "Age":54,
    "Fare":26
  },
  {
    "PassengerId":583,
    "Survived":"0",
    "Pclass":2,
    "Sex":"male",
    "Age":54,
    "Fare":26
  },
  {
    "PassengerId":16,
    "Survived":"1",
    "Pclass":2,
    "Sex":"female",
    "Age":55,
    "Fare":16
  },
  {
    "PassengerId":773,
    "Survived":"0",
    "Pclass":2,
    "Sex":"female",
    "Age":57,
    "Fare":10.5
  },
  {
    "PassengerId":627,
    "Survived":"0",
    "Pclass":2,
    "Sex":"male",
    "Age":57,
    "Fare":12.35
  },
  {
    "PassengerId":233,
    "Survived":"0",
    "Pclass":2,
    "Sex":"male",
    "Age":59,
    "Fare":13.5
  },
  {
    "PassengerId":685,
    "Survived":"0",
    "Pclass":2,
    "Sex":"male",
    "Age":60,
    "Fare":39
  },
  {
    "PassengerId":571,
    "Survived":"1",
    "Pclass":2,
    "Sex":"male",
    "Age":62,
    "Fare":10.5
  },
  {
    "PassengerId":34,
    "Survived":"0",
    "Pclass":2,
    "Sex":"male",
    "Age":66,
    "Fare":10.5
  },
  {
    "PassengerId":673,
    "Survived":"0",
    "Pclass":2,
    "Sex":"male",
    "Age":70,
    "Fare":10.5
  },
  {
    "PassengerId":804,
    "Survived":"1",
    "Pclass":3,
    "Sex":"male",
    "Age":0.42,
    "Fare":8.5167
  },
  {
    "PassengerId":645,
    "Survived":"1",
    "Pclass":3,
    "Sex":"female",
    "Age":0.75,
    "Fare":19.2583
  },
  {
    "PassengerId":470,
    "Survived":"1",
    "Pclass":3,
    "Sex":"female",
    "Age":0.75,
    "Fare":19.2583
  },
  {
    "PassengerId":173,
    "Survived":"1",
    "Pclass":3,
    "Sex":"female",
    "Age":1,
    "Fare":11.1333
  },
  {
    "PassengerId":382,
    "Survived":"1",
    "Pclass":3,
    "Sex":"female",
    "Age":1,
    "Fare":15.7417
  },
  {
    "PassengerId":789,
    "Survived":"1",
    "Pclass":3,
    "Sex":"male",
    "Age":1,
    "Fare":20.575
  },
  {
    "PassengerId":165,
    "Survived":"0",
    "Pclass":3,
    "Sex":"male",
    "Age":1,
    "Fare":39.6875
  },
  {
    "PassengerId":387,
    "Survived":"0",
    "Pclass":3,
    "Sex":"male",
    "Age":1,
    "Fare":46.9
  },
  {
    "PassengerId":206,
    "Survived":"0",
    "Pclass":3,
    "Sex":"female",
    "Age":2,
    "Fare":10.4625
  },
  {
    "PassengerId":480,
    "Survived":"1",
    "Pclass":3,
    "Sex":"female",
    "Age":2,
    "Fare":12.2875
  },
  {
    "PassengerId":8,
    "Survived":"0",
    "Pclass":3,
    "Sex":"male",
    "Age":2,
    "Fare":21.075
  },
  {
    "PassengerId":643,
    "Survived":"0",
    "Pclass":3,
    "Sex":"female",
    "Age":2,
    "Fare":27.9
  },
  {
    "PassengerId":17,
    "Survived":"0",
    "Pclass":3,
    "Sex":"male",
    "Age":2,
    "Fare":29.125
  },
  {
    "PassengerId":120,
    "Survived":"0",
    "Pclass":3,
    "Sex":"female",
    "Age":2,
    "Fare":31.275
  },
  {
    "PassengerId":825,
    "Survived":"0",
    "Pclass":3,
    "Sex":"male",
    "Age":2,
    "Fare":39.6875
  },
  {
    "PassengerId":349,
    "Survived":"1",
    "Pclass":3,
    "Sex":"male",
    "Age":3,
    "Fare":15.9
  },
  {
    "PassengerId":375,
    "Survived":"0",
    "Pclass":3,
    "Sex":"female",
    "Age":3,
    "Fare":21.075
  },
  {
    "PassengerId":262,
    "Survived":"1",
    "Pclass":3,
    "Sex":"male",
    "Age":3,
    "Fare":31.3875
  },
  {
    "PassengerId":870,
    "Survived":"1",
    "Pclass":3,
    "Sex":"male",
    "Age":4,
    "Fare":11.1333
  },
  {
    "PassengerId":692,
    "Survived":"1",
    "Pclass":3,
    "Sex":"female",
    "Age":4,
    "Fare":13.4167
  },
  {
    "PassengerId":11,
    "Survived":"1",
    "Pclass":3,
    "Sex":"female",
    "Age":4,
    "Fare":16.7
  },
  {
    "PassengerId":185,
    "Survived":"1",
    "Pclass":3,
    "Sex":"female",
    "Age":4,
    "Fare":22.025
  },
  {
    "PassengerId":64,
    "Survived":"0",
    "Pclass":3,
    "Sex":"male",
    "Age":4,
    "Fare":27.9
  },
  {
    "PassengerId":172,
    "Survived":"0",
    "Pclass":3,
    "Sex":"male",
    "Age":4,
    "Fare":29.125
  },
  {
    "PassengerId":851,
    "Survived":"0",
    "Pclass":3,
    "Sex":"male",
    "Age":4,
    "Fare":31.275
  },
  {
    "PassengerId":778,
    "Survived":"1",
    "Pclass":3,
    "Sex":"female",
    "Age":5,
    "Fare":12.475
  },
  {
    "PassengerId":449,
    "Survived":"1",
    "Pclass":3,
    "Sex":"female",
    "Age":5,
    "Fare":19.2583
  },
  {
    "PassengerId":234,
    "Survived":"1",
    "Pclass":3,
    "Sex":"female",
    "Age":5,
    "Fare":31.3875
  },
  {
    "PassengerId":752,
    "Survived":"1",
    "Pclass":3,
    "Sex":"male",
    "Age":6,
    "Fare":12.475
  },
  {
    "PassengerId":814,
    "Survived":"0",
    "Pclass":3,
    "Sex":"female",
    "Age":6,
    "Fare":31.275
  },
  {
    "PassengerId":279,
    "Survived":"0",
    "Pclass":3,
    "Sex":"male",
    "Age":7,
    "Fare":29.125
  },
  {
    "PassengerId":51,
    "Survived":"0",
    "Pclass":3,
    "Sex":"male",
    "Age":7,
    "Fare":39.6875
  },
  {
    "PassengerId":25,
    "Survived":"0",
    "Pclass":3,
    "Sex":"female",
    "Age":8,
    "Fare":21.075
  },
  {
    "PassengerId":788,
    "Survived":"0",
    "Pclass":3,
    "Sex":"male",
    "Age":8,
    "Fare":29.125
  },
  {
    "PassengerId":853,
    "Survived":"0",
    "Pclass":3,
    "Sex":"female",
    "Age":9,
    "Fare":15.2458
  },
  {
    "PassengerId":490,
    "Survived":"1",
    "Pclass":3,
    "Sex":"male",
    "Age":9,
    "Fare":15.9
  },
  {
    "PassengerId":166,
    "Survived":"1",
    "Pclass":3,
    "Sex":"male",
    "Age":9,
    "Fare":20.525
  },
  {
    "PassengerId":635,
    "Survived":"0",
    "Pclass":3,
    "Sex":"female",
    "Age":9,
    "Fare":27.9
  },
  {
    "PassengerId":542,
    "Survived":"0",
    "Pclass":3,
    "Sex":"female",
    "Age":9,
    "Fare":31.275
  },
  {
    "PassengerId":183,
    "Survived":"0",
    "Pclass":3,
    "Sex":"male",
    "Age":9,
    "Fare":31.3875
  },
  {
    "PassengerId":148,
    "Survived":"0",
    "Pclass":3,
    "Sex":"female",
    "Age":9,
    "Fare":34.375
  },
  {
    "PassengerId":481,
    "Survived":"0",
    "Pclass":3,
    "Sex":"male",
    "Age":9,
    "Fare":46.9
  },
  {
    "PassengerId":420,
    "Survived":"0",
    "Pclass":3,
    "Sex":"female",
    "Age":10,
    "Fare":24.15
  },
  {
    "PassengerId":820,
    "Survived":"0",
    "Pclass":3,
    "Sex":"male",
    "Age":10,
    "Fare":27.9
  },
  {
    "PassengerId":732,
    "Survived":"0",
    "Pclass":3,
    "Sex":"male",
    "Age":11,
    "Fare":18.7875
  },
  {
    "PassengerId":543,
    "Survived":"0",
    "Pclass":3,
    "Sex":"female",
    "Age":11,
    "Fare":31.275
  },
  {
    "PassengerId":60,
    "Survived":"0",
    "Pclass":3,
    "Sex":"male",
    "Age":11,
    "Fare":46.9
  },
  {
    "PassengerId":126,
    "Survived":"1",
    "Pclass":3,
    "Sex":"male",
    "Age":12,
    "Fare":11.2417
  },
  {
    "PassengerId":781,
    "Survived":"1",
    "Pclass":3,
    "Sex":"female",
    "Age":13,
    "Fare":7.2292
  },
  {
    "PassengerId":15,
    "Survived":"0",
    "Pclass":3,
    "Sex":"female",
    "Age":14,
    "Fare":7.8542
  },
  {
    "PassengerId":40,
    "Survived":"1",
    "Pclass":3,
    "Sex":"female",
    "Age":14,
    "Fare":11.2417
  },
  {
    "PassengerId":687,
    "Survived":"0",
    "Pclass":3,
    "Sex":"male",
    "Age":14,
    "Fare":39.6875
  },
  {
    "PassengerId":684,
    "Survived":"0",
    "Pclass":3,
    "Sex":"male",
    "Age":14,
    "Fare":46.9
  },
  {
    "PassengerId":112,
    "Survived":"0",
    "Pclass":3,
    "Sex":"female",
    "Age":14.5,
    "Fare":14.4542
  },
  {
    "PassengerId":876,
    "Survived":"1",
    "Pclass":3,
    "Sex":"female",
    "Age":15,
    "Fare":7.225
  },
  {
    "PassengerId":353,
    "Survived":"0",
    "Pclass":3,
    "Sex":"male",
    "Age":15,
    "Fare":7.2292
  },
  {
    "PassengerId":23,
    "Survived":"1",
    "Pclass":3,
    "Sex":"female",
    "Age":15,
    "Fare":8.0292
  },
  {
    "PassengerId":831,
    "Survived":"1",
    "Pclass":3,
    "Sex":"female",
    "Age":15,
    "Fare":14.4542
  },
  {
    "PassengerId":157,
    "Survived":"1",
    "Pclass":3,
    "Sex":"female",
    "Age":16,
    "Fare":7.7333
  },
  {
    "PassengerId":209,
    "Survived":"1",
    "Pclass":3,
    "Sex":"female",
    "Age":16,
    "Fare":7.75
  },
  {
    "PassengerId":765,
    "Survived":"0",
    "Pclass":3,
    "Sex":"male",
    "Age":16,
    "Fare":7.775
  },
  {
    "PassengerId":575,
    "Survived":"0",
    "Pclass":3,
    "Sex":"male",
    "Age":16,
    "Fare":8.05
  },
  {
    "PassengerId":221,
    "Survived":"1",
    "Pclass":3,
    "Sex":"male",
    "Age":16,
    "Fare":8.05
  },
  {
    "PassengerId":139,
    "Survived":"0",
    "Pclass":3,
    "Sex":"male",
    "Age":16,
    "Fare":9.2167
  },
  {
    "PassengerId":283,
    "Survived":"0",
    "Pclass":3,
    "Sex":"male",
    "Age":16,
    "Fare":9.5
  },
  {
    "PassengerId":334,
    "Survived":"0",
    "Pclass":3,
    "Sex":"male",
    "Age":16,
    "Fare":18
  },
  {
    "PassengerId":747,
    "Survived":"0",
    "Pclass":3,
    "Sex":"male",
    "Age":16,
    "Fare":20.25
  },
  {
    "PassengerId":87,
    "Survived":"0",
    "Pclass":3,
    "Sex":"male",
    "Age":16,
    "Fare":34.375
  },
  {
    "PassengerId":267,
    "Survived":"0",
    "Pclass":3,
    "Sex":"male",
    "Age":16,
    "Fare":39.6875
  },
  {
    "PassengerId":72,
    "Survived":"0",
    "Pclass":3,
    "Sex":"female",
    "Age":16,
    "Fare":46.9
  },
  {
    "PassengerId":722,
    "Survived":"0",
    "Pclass":3,
    "Sex":"male",
    "Age":17,
    "Fare":7.0542
  },
  {
    "PassengerId":434,
    "Survived":"0",
    "Pclass":3,
    "Sex":"male",
    "Age":17,
    "Fare":7.125
  },
  {
    "PassengerId":533,
    "Survived":"0",
    "Pclass":3,
    "Sex":"male",
    "Age":17,
    "Fare":7.2292
  },
  {
    "PassengerId":69,
    "Survived":"1",
    "Pclass":3,
    "Sex":"female",
    "Age":17,
    "Fare":7.925
  },
  {
    "PassengerId":845,
    "Survived":"0",
    "Pclass":3,
    "Sex":"male",
    "Age":17,
    "Fare":8.6625
  },
  {
    "PassengerId":501,
    "Survived":"0",
    "Pclass":3,
    "Sex":"male",
    "Age":17,
    "Fare":8.6625
  },
  {
    "PassengerId":164,
    "Survived":"0",
    "Pclass":3,
    "Sex":"male",
    "Age":17,
    "Fare":8.6625
  },
  {
    "PassengerId":115,
    "Survived":"0",
    "Pclass":3,
    "Sex":"female",
    "Age":17,
    "Fare":14.4583
  },
  {
    "PassengerId":372,
    "Survived":"0",
    "Pclass":3,
    "Sex":"male",
    "Age":18,
    "Fare":6.4958
  },
  {
    "PassengerId":655,
    "Survived":"0",
    "Pclass":3,
    "Sex":"female",
    "Age":18,
    "Fare":6.75
  },
  {
    "PassengerId":787,
    "Survived":"1",
    "Pclass":3,
    "Sex":"female",
    "Age":18,
    "Fare":7.4958
  },
  {
    "PassengerId":776,
    "Survived":"0",
    "Pclass":3,
    "Sex":"male",
    "Age":18,
    "Fare":7.75
  },
  {
    "PassengerId":808,
    "Survived":"0",
    "Pclass":3,
    "Sex":"female",
    "Age":18,
    "Fare":7.775
  },
  {
    "PassengerId":676,
    "Survived":"0",
    "Pclass":3,
    "Sex":"male",
    "Age":18,
    "Fare":7.775
  },
  {
    "PassengerId":689,
    "Survived":"0",
    "Pclass":3,
    "Sex":"male",
    "Age":18,
    "Fare":7.7958
  },
  {
    "PassengerId":176,
    "Survived":"0",
    "Pclass":3,
    "Sex":"male",
    "Age":18,
    "Fare":7.8542
  },
  {
    "PassengerId":205,
    "Survived":"1",
    "Pclass":3,
    "Sex":"male",
    "Age":18,
    "Fare":8.05
  },
  {
    "PassengerId":835,
    "Survived":"0",
    "Pclass":3,
    "Sex":"male",
    "Age":18,
    "Fare":8.3
  },
  {
    "PassengerId":856,
    "Survived":"1",
    "Pclass":3,
    "Sex":"female",
    "Age":18,
    "Fare":9.35
  },
  {
    "PassengerId":678,
    "Survived":"1",
    "Pclass":3,
    "Sex":"female",
    "Age":18,
    "Fare":9.8417
  },
  {
    "PassengerId":703,
    "Survived":"0",
    "Pclass":3,
    "Sex":"female",
    "Age":18,
    "Fare":14.4542
  },
  {
    "PassengerId":50,
    "Survived":"0",
    "Pclass":3,
    "Sex":"female",
    "Age":18,
    "Fare":17.8
  },
  {
    "PassengerId":39,
    "Survived":"0",
    "Pclass":3,
    "Sex":"female",
    "Age":18,
    "Fare":18
  },
  {
    "PassengerId":425,
    "Survived":"0",
    "Pclass":3,
    "Sex":"male",
    "Age":18,
    "Fare":20.2125
  },
  {
    "PassengerId":303,
    "Survived":"0",
    "Pclass":3,
    "Sex":"male",
    "Age":19,
    "Fare":0
  },
  {
    "PassengerId":144,
    "Survived":"0",
    "Pclass":3,
    "Sex":"male",
    "Age":19,
    "Fare":6.75
  },
  {
    "PassengerId":716,
    "Survived":"0",
    "Pclass":3,
    "Sex":"male",
    "Age":19,
    "Fare":7.65
  },
  {
    "PassengerId":380,
    "Survived":"0",
    "Pclass":3,
    "Sex":"male",
    "Age":19,
    "Fare":7.775
  },
  {
    "PassengerId":193,
    "Survived":"1",
    "Pclass":3,
    "Sex":"female",
    "Age":19,
    "Fare":7.8542
  },
  {
    "PassengerId":45,
    "Survived":"1",
    "Pclass":3,
    "Sex":"female",
    "Age":19,
    "Fare":7.8792
  },
  {
    "PassengerId":647,
    "Survived":"0",
    "Pclass":3,
    "Sex":"male",
    "Age":19,
    "Fare":7.8958
  },
  {
    "PassengerId":878,
    "Survived":"0",
    "Pclass":3,
    "Sex":"male",
    "Age":19,
    "Fare":7.8958
  },
  {
    "PassengerId":567,
    "Survived":"0",
    "Pclass":3,
    "Sex":"male",
    "Age":19,
    "Fare":7.8958
  },
  {
    "PassengerId":284,
    "Survived":"1",
    "Pclass":3,
    "Sex":"male",
    "Age":19,
    "Fare":8.05
  },
  {
    "PassengerId":373,
    "Survived":"0",
    "Pclass":3,
    "Sex":"male",
    "Age":19,
    "Fare":8.05
  },
  {
    "PassengerId":68,
    "Survived":"0",
    "Pclass":3,
    "Sex":"male",
    "Age":19,
    "Fare":8.1583
  },
  {
    "PassengerId":688,
    "Survived":"0",
    "Pclass":3,
    "Sex":"male",
    "Age":19,
    "Fare":10.1708
  },
  {
    "PassengerId":576,
    "Survived":"0",
    "Pclass":3,
    "Sex":"male",
    "Age":19,
    "Fare":14.5
  },
  {
    "PassengerId":379,
    "Survived":"0",
    "Pclass":3,
    "Sex":"male",
    "Age":20,
    "Fare":4.0125
  },
  {
    "PassengerId":132,
    "Survived":"0",
    "Pclass":3,
    "Sex":"male",
    "Age":20,
    "Fare":7.05
  },
  {
    "PassengerId":763,
    "Survived":"1",
    "Pclass":3,
    "Sex":"male",
    "Age":20,
    "Fare":7.2292
  },
  {
    "PassengerId":641,
    "Survived":"0",
    "Pclass":3,
    "Sex":"male",
    "Age":20,
    "Fare":7.8542
  },
  {
    "PassengerId":92,
    "Survived":"0",
    "Pclass":3,
    "Sex":"male",
    "Age":20,
    "Fare":7.8542
  },
  {
    "PassengerId":665,
    "Survived":"1",
    "Pclass":3,
    "Sex":"male",
    "Age":20,
    "Fare":7.925
  },
  {
    "PassengerId":841,
    "Survived":"0",
    "Pclass":3,
    "Sex":"male",
    "Age":20,
    "Fare":7.925
  },
  {
    "PassengerId":13,
    "Survived":"0",
    "Pclass":3,
    "Sex":"male",
    "Age":20,
    "Fare":8.05
  },
  {
    "PassengerId":726,
    "Survived":"0",
    "Pclass":3,
    "Sex":"male",
    "Age":20,
    "Fare":8.6625
  },
  {
    "PassengerId":405,
    "Survived":"0",
    "Pclass":3,
    "Sex":"female",
    "Age":20,
    "Fare":8.6625
  },
  {
    "PassengerId":683,
    "Survived":"0",
    "Pclass":3,
    "Sex":"male",
    "Age":20,
    "Fare":9.225
  },
  {
    "PassengerId":442,
    "Survived":"0",
    "Pclass":3,
    "Sex":"male",
    "Age":20,
    "Fare":9.5
  },
  {
    "PassengerId":114,
    "Survived":"0",
    "Pclass":3,
    "Sex":"female",
    "Age":20,
    "Fare":9.825
  },
  {
    "PassengerId":877,
    "Survived":"0",
    "Pclass":3,
    "Sex":"male",
    "Age":20,
    "Fare":9.8458
  },
  {
    "PassengerId":623,
    "Survived":"1",
    "Pclass":3,
    "Sex":"male",
    "Age":20,
    "Fare":15.7417
  },
  {
    "PassengerId":228,
    "Survived":"0",
    "Pclass":3,
    "Sex":"male",
    "Age":20.5,
    "Fare":7.25
  },
  {
    "PassengerId":492,
    "Survived":"0",
    "Pclass":3,
    "Sex":"male",
    "Age":21,
    "Fare":7.25
  },
  {
    "PassengerId":107,
    "Survived":"1",
    "Pclass":3,
    "Sex":"female",
    "Age":21,
    "Fare":7.65
  },
  {
    "PassengerId":422,
    "Survived":"0",
    "Pclass":3,
    "Sex":"male",
    "Age":21,
    "Fare":7.7333
  },
  {
    "PassengerId":502,
    "Survived":"0",
    "Pclass":3,
    "Sex":"female",
    "Age":21,
    "Fare":7.75
  },
  {
    "PassengerId":409,
    "Survived":"0",
    "Pclass":3,
    "Sex":"male",
    "Age":21,
    "Fare":7.775
  },
  {
    "PassengerId":392,
    "Survived":"1",
    "Pclass":3,
    "Sex":"male",
    "Age":21,
    "Fare":7.7958
  },
  {
    "PassengerId":52,
    "Survived":"0",
    "Pclass":3,
    "Sex":"male",
    "Age":21,
    "Fare":7.8
  },
  {
    "PassengerId":624,
    "Survived":"0",
    "Pclass":3,
    "Sex":"male",
    "Age":21,
    "Fare":7.8542
  },
  {
    "PassengerId":116,
    "Survived":"0",
    "Pclass":3,
    "Sex":"male",
    "Age":21,
    "Fare":7.925
  },
  {
    "PassengerId":174,
    "Survived":"0",
    "Pclass":3,
    "Sex":"male",
    "Age":21,
    "Fare":7.925
  },
  {
    "PassengerId":38,
    "Survived":"0",
    "Pclass":3,
    "Sex":"male",
    "Age":21,
    "Fare":8.05
  },
  {
    "PassengerId":495,
    "Survived":"0",
    "Pclass":3,
    "Sex":"male",
    "Age":21,
    "Fare":8.05
  },
  {
    "PassengerId":653,
    "Survived":"0",
    "Pclass":3,
    "Sex":"male",
    "Age":21,
    "Fare":8.4333
  },
  {
    "PassengerId":837,
    "Survived":"0",
    "Pclass":3,
    "Sex":"male",
    "Age":21,
    "Fare":8.6625
  },
  {
    "PassengerId":403,
    "Survived":"0",
    "Pclass":3,
    "Sex":"female",
    "Age":21,
    "Fare":9.825
  },
  {
    "PassengerId":625,
    "Survived":"0",
    "Pclass":3,
    "Sex":"male",
    "Age":21,
    "Fare":16.1
  },
  {
    "PassengerId":437,
    "Survived":"0",
    "Pclass":3,
    "Sex":"female",
    "Age":21,
    "Fare":34.375
  },
  {
    "PassengerId":244,
    "Survived":"0",
    "Pclass":3,
    "Sex":"male",
    "Age":22,
    "Fare":7.125
  },
  {
    "PassengerId":554,
    "Survived":"1",
    "Pclass":3,
    "Sex":"male",
    "Age":22,
    "Fare":7.225
  },
  {
    "PassengerId":61,
    "Survived":"0",
    "Pclass":3,
    "Sex":"male",
    "Age":22,
    "Fare":7.2292
  },
  {
    "PassengerId":213,
    "Survived":"0",
    "Pclass":3,
    "Sex":"male",
    "Age":22,
    "Fare":7.25
  },
  {
    "PassengerId":377,
    "Survived":"1",
    "Pclass":3,
    "Sex":"female",
    "Age":22,
    "Fare":7.25
  },
  {
    "PassengerId":1,
    "Survived":"0",
    "Pclass":3,
    "Sex":"male",
    "Age":22,
    "Fare":7.25
  },
  {
    "PassengerId":321,
    "Survived":"0",
    "Pclass":3,
    "Sex":"male",
    "Age":22,
    "Fare":7.25
  },
  {
    "PassengerId":479,
    "Survived":"0",
    "Pclass":3,
    "Sex":"male",
    "Age":22,
    "Fare":7.5208
  },
  {
    "PassengerId":142,
    "Survived":"1",
    "Pclass":3,
    "Sex":"female",
    "Age":22,
    "Fare":7.75
  },
  {
    "PassengerId":290,
    "Survived":"1",
    "Pclass":3,
    "Sex":"female",
    "Age":22,
    "Fare":7.75
  },
  {
    "PassengerId":555,
    "Survived":"1",
    "Pclass":3,
    "Sex":"female",
    "Age":22,
    "Fare":7.775
  },
  {
    "PassengerId":396,
    "Survived":"0",
    "Pclass":3,
    "Sex":"male",
    "Age":22,
    "Fare":7.7958
  },
  {
    "PassengerId":288,
    "Survived":"0",
    "Pclass":3,
    "Sex":"male",
    "Age":22,
    "Fare":7.8958
  },
  {
    "PassengerId":522,
    "Survived":"0",
    "Pclass":3,
    "Sex":"male",
    "Age":22,
    "Fare":7.8958
  },
  {
    "PassengerId":589,
    "Survived":"0",
    "Pclass":3,
    "Sex":"male",
    "Age":22,
    "Fare":8.05
  },
  {
    "PassengerId":113,
    "Survived":"0",
    "Pclass":3,
    "Sex":"male",
    "Age":22,
    "Fare":8.05
  },
  {
    "PassengerId":81,
    "Survived":"0",
    "Pclass":3,
    "Sex":"male",
    "Age":22,
    "Fare":9
  },
  {
    "PassengerId":226,
    "Survived":"0",
    "Pclass":3,
    "Sex":"male",
    "Age":22,
    "Fare":9.35
  },
  {
    "PassengerId":475,
    "Survived":"0",
    "Pclass":3,
    "Sex":"female",
    "Age":22,
    "Fare":9.8375
  },
  {
    "PassengerId":883,
    "Survived":"0",
    "Pclass":3,
    "Sex":"female",
    "Age":22,
    "Fare":10.5167
  },
  {
    "PassengerId":650,
    "Survived":"1",
    "Pclass":3,
    "Sex":"female",
    "Age":23,
    "Fare":7.55
  },
  {
    "PassengerId":834,
    "Survived":"0",
    "Pclass":3,
    "Sex":"male",
    "Age":23,
    "Fare":7.8542
  },
  {
    "PassengerId":754,
    "Survived":"0",
    "Pclass":3,
    "Sex":"male",
    "Age":23,
    "Fare":7.8958
  },
  {
    "PassengerId":817,
    "Survived":"0",
    "Pclass":3,
    "Sex":"female",
    "Age":23,
    "Fare":7.925
  },
  {
    "PassengerId":351,
    "Survived":"0",
    "Pclass":3,
    "Sex":"male",
    "Age":23,
    "Fare":9.225
  },
  {
    "PassengerId":297,
    "Survived":"0",
    "Pclass":3,
    "Sex":"male",
    "Age":23.5,
    "Fare":7.2292
  },
  {
    "PassengerId":211,
    "Survived":"0",
    "Pclass":3,
    "Sex":"male",
    "Age":24,
    "Fare":7.05
  },
  {
    "PassengerId":128,
    "Survived":"1",
    "Pclass":3,
    "Sex":"male",
    "Age":24,
    "Fare":7.1417
  },
  {
    "PassengerId":515,
    "Survived":"0",
    "Pclass":3,
    "Sex":"male",
    "Age":24,
    "Fare":7.4958
  },
  {
    "PassengerId":500,
    "Survived":"0",
    "Pclass":3,
    "Sex":"male",
    "Age":24,
    "Fare":7.7958
  },
  {
    "PassengerId":295,
    "Survived":"0",
    "Pclass":3,
    "Sex":"male",
    "Age":24,
    "Fare":7.8958
  },
  {
    "PassengerId":90,
    "Survived":"0",
    "Pclass":3,
    "Sex":"male",
    "Age":24,
    "Fare":8.05
  },
  {
    "PassengerId":294,
    "Survived":"0",
    "Pclass":3,
    "Sex":"female",
    "Age":24,
    "Fare":8.85
  },
  {
    "PassengerId":771,
    "Survived":"0",
    "Pclass":3,
    "Sex":"male",
    "Age":24,
    "Fare":9.5
  },
  {
    "PassengerId":143,
    "Survived":"1",
    "Pclass":3,
    "Sex":"female",
    "Age":24,
    "Fare":15.85
  },
  {
    "PassengerId":744,
    "Survived":"0",
    "Pclass":3,
    "Sex":"male",
    "Age":24,
    "Fare":16.1
  },
  {
    "PassengerId":395,
    "Survived":"1",
    "Pclass":3,
    "Sex":"female",
    "Age":24,
    "Fare":16.7
  },
  {
    "PassengerId":859,
    "Survived":"1",
    "Pclass":3,
    "Sex":"female",
    "Age":24,
    "Fare":19.2583
  },
  {
    "PassengerId":566,
    "Survived":"0",
    "Pclass":3,
    "Sex":"male",
    "Age":24,
    "Fare":24.15
  },
  {
    "PassengerId":677,
    "Survived":"0",
    "Pclass":3,
    "Sex":"male",
    "Age":24.5,
    "Fare":8.05
  },
  {
    "PassengerId":272,
    "Survived":"1",
    "Pclass":3,
    "Sex":"male",
    "Age":25,
    "Fare":0
  },
  {
    "PassengerId":885,
    "Survived":"0",
    "Pclass":3,
    "Sex":"male",
    "Age":25,
    "Fare":7.05
  },
  {
    "PassengerId":785,
    "Survived":"0",
    "Pclass":3,
    "Sex":"male",
    "Age":25,
    "Fare":7.05
  },
  {
    "PassengerId":694,
    "Survived":"0",
    "Pclass":3,
    "Sex":"male",
    "Age":25,
    "Fare":7.225
  },
  {
    "PassengerId":786,
    "Survived":"0",
    "Pclass":3,
    "Sex":"male",
    "Age":25,
    "Fare":7.25
  },
  {
    "PassengerId":76,
    "Survived":"0",
    "Pclass":3,
    "Sex":"male",
    "Age":25,
    "Fare":7.65
  },
  {
    "PassengerId":704,
    "Survived":"0",
    "Pclass":3,
    "Sex":"male",
    "Age":25,
    "Fare":7.7417
  },
  {
    "PassengerId":443,
    "Survived":"0",
    "Pclass":3,
    "Sex":"male",
    "Age":25,
    "Fare":7.775
  },
  {
    "PassengerId":247,
    "Survived":"0",
    "Pclass":3,
    "Sex":"female",
    "Age":25,
    "Fare":7.775
  },
  {
    "PassengerId":268,
    "Survived":"1",
    "Pclass":3,
    "Sex":"male",
    "Age":25,
    "Fare":7.775
  },
  {
    "PassengerId":795,
    "Survived":"0",
    "Pclass":3,
    "Sex":"male",
    "Age":25,
    "Fare":7.8958
  },
  {
    "PassengerId":730,
    "Survived":"0",
    "Pclass":3,
    "Sex":"female",
    "Age":25,
    "Fare":7.925
  },
  {
    "PassengerId":354,
    "Survived":"0",
    "Pclass":3,
    "Sex":"male",
    "Age":25,
    "Fare":17.8
  },
  {
    "PassengerId":163,
    "Survived":"0",
    "Pclass":3,
    "Sex":"male",
    "Age":26,
    "Fare":7.775
  },
  {
    "PassengerId":705,
    "Survived":"0",
    "Pclass":3,
    "Sex":"male",
    "Age":26,
    "Fare":7.8542
  },
  {
    "PassengerId":316,
    "Survived":"1",
    "Pclass":3,
    "Sex":"female",
    "Age":26,
    "Fare":7.8542
  },
  {
    "PassengerId":811,
    "Survived":"0",
    "Pclass":3,
    "Sex":"male",
    "Age":26,
    "Fare":7.8875
  },
  {
    "PassengerId":871,
    "Survived":"0",
    "Pclass":3,
    "Sex":"male",
    "Age":26,
    "Fare":7.8958
  },
  {
    "PassengerId":629,
    "Survived":"0",
    "Pclass":3,
    "Sex":"male",
    "Age":26,
    "Fare":7.8958
  },
  {
    "PassengerId":3,
    "Survived":"1",
    "Pclass":3,
    "Sex":"female",
    "Age":26,
    "Fare":7.925
  },
  {
    "PassengerId":402,
    "Survived":"0",
    "Pclass":3,
    "Sex":"male",
    "Age":26,
    "Fare":8.05
  },
  {
    "PassengerId":70,
    "Survived":"0",
    "Pclass":3,
    "Sex":"male",
    "Age":26,
    "Fare":8.6625
  },
  {
    "PassengerId":74,
    "Survived":"0",
    "Pclass":3,
    "Sex":"male",
    "Age":26,
    "Fare":14.4542
  },
  {
    "PassengerId":618,
    "Survived":"0",
    "Pclass":3,
    "Sex":"female",
    "Age":26,
    "Fare":16.1
  },
  {
    "PassengerId":208,
    "Survived":"1",
    "Pclass":3,
    "Sex":"male",
    "Age":26,
    "Fare":18.7875
  },
  {
    "PassengerId":94,
    "Survived":"0",
    "Pclass":3,
    "Sex":"male",
    "Age":26,
    "Fare":20.575
  },
  {
    "PassengerId":510,
    "Survived":"1",
    "Pclass":3,
    "Sex":"male",
    "Age":26,
    "Fare":56.4958
  },
  {
    "PassengerId":805,
    "Survived":"1",
    "Pclass":3,
    "Sex":"male",
    "Age":27,
    "Fare":6.975
  },
  {
    "PassengerId":147,
    "Survived":"1",
    "Pclass":3,
    "Sex":"male",
    "Age":27,
    "Fare":7.7958
  },
  {
    "PassengerId":322,
    "Survived":"0",
    "Pclass":3,
    "Sex":"male",
    "Age":27,
    "Fare":7.8958
  },
  {
    "PassengerId":217,
    "Survived":"1",
    "Pclass":3,
    "Sex":"female",
    "Age":27,
    "Fare":7.925
  },
  {
    "PassengerId":822,
    "Survived":"1",
    "Pclass":3,
    "Sex":"male",
    "Age":27,
    "Fare":8.6625
  },
  {
    "PassengerId":9,
    "Survived":"1",
    "Pclass":3,
    "Sex":"female",
    "Age":27,
    "Fare":11.1333
  },
  {
    "PassengerId":824,
    "Survived":"1",
    "Pclass":3,
    "Sex":"female",
    "Age":27,
    "Fare":12.475
  },
  {
    "PassengerId":621,
    "Survived":"0",
    "Pclass":3,
    "Sex":"male",
    "Age":27,
    "Fare":14.4542
  },
  {
    "PassengerId":757,
    "Survived":"0",
    "Pclass":3,
    "Sex":"male",
    "Age":28,
    "Fare":7.7958
  },
  {
    "PassengerId":282,
    "Survived":"0",
    "Pclass":3,
    "Sex":"male",
    "Age":28,
    "Fare":7.8542
  },
  {
    "PassengerId":101,
    "Survived":"0",
    "Pclass":3,
    "Sex":"female",
    "Age":28,
    "Fare":7.8958
  },
  {
    "PassengerId":314,
    "Survived":"0",
    "Pclass":3,
    "Sex":"male",
    "Age":28,
    "Fare":7.8958
  },
  {
    "PassengerId":106,
    "Survived":"0",
    "Pclass":3,
    "Sex":"male",
    "Age":28,
    "Fare":7.8958
  },
  {
    "PassengerId":393,
    "Survived":"0",
    "Pclass":3,
    "Sex":"male",
    "Age":28,
    "Fare":7.925
  },
  {
    "PassengerId":356,
    "Survived":"0",
    "Pclass":3,
    "Sex":"male",
    "Age":28,
    "Fare":9.5
  },
  {
    "PassengerId":201,
    "Survived":"0",
    "Pclass":3,
    "Sex":"male",
    "Age":28,
    "Fare":9.5
  },
  {
    "PassengerId":424,
    "Survived":"0",
    "Pclass":3,
    "Sex":"female",
    "Age":28,
    "Fare":14.4
  },
  {
    "PassengerId":404,
    "Survived":"0",
    "Pclass":3,
    "Sex":"male",
    "Age":28,
    "Fare":15.85
  },
  {
    "PassengerId":509,
    "Survived":"0",
    "Pclass":3,
    "Sex":"male",
    "Age":28,
    "Fare":22.525
  },
  {
    "PassengerId":170,
    "Survived":"0",
    "Pclass":3,
    "Sex":"male",
    "Age":28,
    "Fare":56.4958
  },
  {
    "PassengerId":58,
    "Survived":"0",
    "Pclass":3,
    "Sex":"male",
    "Age":28.5,
    "Fare":7.2292
  },
  {
    "PassengerId":736,
    "Survived":"0",
    "Pclass":3,
    "Sex":"male",
    "Age":28.5,
    "Fare":16.1
  },
  {
    "PassengerId":478,
    "Survived":"0",
    "Pclass":3,
    "Sex":"male",
    "Age":29,
    "Fare":7.0458
  },
  {
    "PassengerId":511,
    "Survived":"1",
    "Pclass":3,
    "Sex":"male",
    "Age":29,
    "Fare":7.75
  },
  {
    "PassengerId":232,
    "Survived":"0",
    "Pclass":3,
    "Sex":"male",
    "Age":29,
    "Fare":7.775
  },
  {
    "PassengerId":423,
    "Survived":"0",
    "Pclass":3,
    "Sex":"male",
    "Age":29,
    "Fare":7.875
  },
  {
    "PassengerId":456,
    "Survived":"1",
    "Pclass":3,
    "Sex":"male",
    "Age":29,
    "Fare":7.8958
  },
  {
    "PassengerId":91,
    "Survived":"0",
    "Pclass":3,
    "Sex":"male",
    "Age":29,
    "Fare":8.05
  },
  {
    "PassengerId":714,
    "Survived":"0",
    "Pclass":3,
    "Sex":"male",
    "Age":29,
    "Fare":9.4833
  },
  {
    "PassengerId":82,
    "Survived":"1",
    "Pclass":3,
    "Sex":"male",
    "Age":29,
    "Fare":9.5
  },
  {
    "PassengerId":252,
    "Survived":"0",
    "Pclass":3,
    "Sex":"female",
    "Age":29,
    "Fare":10.4625
  },
  {
    "PassengerId":256,
    "Survived":"1",
    "Pclass":3,
    "Sex":"female",
    "Age":29,
    "Fare":15.2458
  },
  {
    "PassengerId":568,
    "Survived":"0",
    "Pclass":3,
    "Sex":"female",
    "Age":29,
    "Fare":21.075
  },
  {
    "PassengerId":245,
    "Survived":"0",
    "Pclass":3,
    "Sex":"male",
    "Age":30,
    "Fare":7.225
  },
  {
    "PassengerId":799,
    "Survived":"0",
    "Pclass":3,
    "Sex":"male",
    "Age":30,
    "Fare":7.2292
  },
  {
    "PassengerId":366,
    "Survived":"0",
    "Pclass":3,
    "Sex":"male",
    "Age":30,
    "Fare":7.25
  },
  {
    "PassengerId":607,
    "Survived":"0",
    "Pclass":3,
    "Sex":"male",
    "Age":30,
    "Fare":7.8958
  },
  {
    "PassengerId":158,
    "Survived":"0",
    "Pclass":3,
    "Sex":"male",
    "Age":30,
    "Fare":8.05
  },
  {
    "PassengerId":489,
    "Survived":"0",
    "Pclass":3,
    "Sex":"male",
    "Age":30,
    "Fare":8.05
  },
  {
    "PassengerId":535,
    "Survived":"0",
    "Pclass":3,
    "Sex":"female",
    "Age":30,
    "Fare":8.6625
  },
  {
    "PassengerId":287,
    "Survived":"1",
    "Pclass":3,
    "Sex":"male",
    "Age":30,
    "Fare":9.5
  },
  {
    "PassengerId":80,
    "Survived":"1",
    "Pclass":3,
    "Sex":"female",
    "Age":30,
    "Fare":12.475
  },
  {
    "PassengerId":254,
    "Survived":"0",
    "Pclass":3,
    "Sex":"male",
    "Age":30,
    "Fare":16.1
  },
  {
    "PassengerId":800,
    "Survived":"0",
    "Pclass":3,
    "Sex":"female",
    "Age":30,
    "Fare":24.15
  },
  {
    "PassengerId":768,
    "Survived":"0",
    "Pclass":3,
    "Sex":"female",
    "Age":30.5,
    "Fare":7.75
  },
  {
    "PassengerId":815,
    "Survived":"0",
    "Pclass":3,
    "Sex":"male",
    "Age":30.5,
    "Fare":8.05
  },
  {
    "PassengerId":750,
    "Survived":"0",
    "Pclass":3,
    "Sex":"male",
    "Age":31,
    "Fare":7.75
  },
  {
    "PassengerId":806,
    "Survived":"0",
    "Pclass":3,
    "Sex":"male",
    "Age":31,
    "Fare":7.775
  },
  {
    "PassengerId":397,
    "Survived":"0",
    "Pclass":3,
    "Sex":"female",
    "Age":31,
    "Fare":7.8542
  },
  {
    "PassengerId":745,
    "Survived":"1",
    "Pclass":3,
    "Sex":"male",
    "Age":31,
    "Fare":7.925
  },
  {
    "PassengerId":798,
    "Survived":"1",
    "Pclass":3,
    "Sex":"female",
    "Age":31,
    "Fare":8.6833
  },
  {
    "PassengerId":19,
    "Survived":"0",
    "Pclass":3,
    "Sex":"female",
    "Age":31,
    "Fare":18
  },
  {
    "PassengerId":329,
    "Survived":"1",
    "Pclass":3,
    "Sex":"female",
    "Age":31,
    "Fare":20.525
  },
  {
    "PassengerId":891,
    "Survived":"0",
    "Pclass":3,
    "Sex":"male",
    "Age":32,
    "Fare":7.75
  },
  {
    "PassengerId":570,
    "Survived":"1",
    "Pclass":3,
    "Sex":"male",
    "Age":32,
    "Fare":7.8542
  },
  {
    "PassengerId":520,
    "Survived":"0",
    "Pclass":3,
    "Sex":"male",
    "Age":32,
    "Fare":7.8958
  },
  {
    "PassengerId":383,
    "Survived":"0",
    "Pclass":3,
    "Sex":"male",
    "Age":32,
    "Fare":7.925
  },
  {
    "PassengerId":580,
    "Survived":"1",
    "Pclass":3,
    "Sex":"male",
    "Age":32,
    "Fare":7.925
  },
  {
    "PassengerId":637,
    "Survived":"0",
    "Pclass":3,
    "Sex":"male",
    "Age":32,
    "Fare":7.925
  },
  {
    "PassengerId":430,
    "Survived":"1",
    "Pclass":3,
    "Sex":"male",
    "Age":32,
    "Fare":8.05
  },
  {
    "PassengerId":770,
    "Survived":"0",
    "Pclass":3,
    "Sex":"male",
    "Age":32,
    "Fare":8.3625
  },
  {
    "PassengerId":658,
    "Survived":"0",
    "Pclass":3,
    "Sex":"female",
    "Age":32,
    "Fare":15.5
  },
  {
    "PassengerId":207,
    "Survived":"0",
    "Pclass":3,
    "Sex":"male",
    "Age":32,
    "Fare":15.85
  },
  {
    "PassengerId":839,
    "Survived":"1",
    "Pclass":3,
    "Sex":"male",
    "Age":32,
    "Fare":56.4958
  },
  {
    "PassengerId":75,
    "Survived":"1",
    "Pclass":3,
    "Sex":"male",
    "Age":32,
    "Fare":56.4958
  },
  {
    "PassengerId":720,
    "Survived":"0",
    "Pclass":3,
    "Sex":"male",
    "Age":33,
    "Fare":7.775
  },
  {
    "PassengerId":882,
    "Survived":"0",
    "Pclass":3,
    "Sex":"male",
    "Age":33,
    "Fare":7.8958
  },
  {
    "PassengerId":131,
    "Survived":"0",
    "Pclass":3,
    "Sex":"male",
    "Age":33,
    "Fare":7.8958
  },
  {
    "PassengerId":104,
    "Survived":"0",
    "Pclass":3,
    "Sex":"male",
    "Age":33,
    "Fare":8.6542
  },
  {
    "PassengerId":286,
    "Survived":"0",
    "Pclass":3,
    "Sex":"male",
    "Age":33,
    "Fare":8.6625
  },
  {
    "PassengerId":753,
    "Survived":"0",
    "Pclass":3,
    "Sex":"male",
    "Age":33,
    "Fare":9.5
  },
  {
    "PassengerId":86,
    "Survived":"1",
    "Pclass":3,
    "Sex":"female",
    "Age":33,
    "Fare":15.85
  },
  {
    "PassengerId":549,
    "Survived":"0",
    "Pclass":3,
    "Sex":"male",
    "Age":33,
    "Fare":20.525
  },
  {
    "PassengerId":203,
    "Survived":"0",
    "Pclass":3,
    "Sex":"male",
    "Age":34,
    "Fare":6.4958
  },
  {
    "PassengerId":462,
    "Survived":"0",
    "Pclass":3,
    "Sex":"male",
    "Age":34,
    "Fare":8.05
  },
  {
    "PassengerId":759,
    "Survived":"0",
    "Pclass":3,
    "Sex":"male",
    "Age":34,
    "Fare":8.05
  },
  {
    "PassengerId":617,
    "Survived":"0",
    "Pclass":3,
    "Sex":"male",
    "Age":34,
    "Fare":14.4
  },
  {
    "PassengerId":844,
    "Survived":"0",
    "Pclass":3,
    "Sex":"male",
    "Age":34.5,
    "Fare":6.4375
  },
  {
    "PassengerId":364,
    "Survived":"0",
    "Pclass":3,
    "Sex":"male",
    "Age":35,
    "Fare":7.05
  },
  {
    "PassengerId":591,
    "Survived":"0",
    "Pclass":3,
    "Sex":"male",
    "Age":35,
    "Fare":7.125
  },
  {
    "PassengerId":848,
    "Survived":"0",
    "Pclass":3,
    "Sex":"male",
    "Age":35,
    "Fare":7.8958
  },
  {
    "PassengerId":5,
    "Survived":"0",
    "Pclass":3,
    "Sex":"male",
    "Age":35,
    "Fare":8.05
  },
  {
    "PassengerId":615,
    "Survived":"0",
    "Pclass":3,
    "Sex":"male",
    "Age":35,
    "Fare":8.05
  },
  {
    "PassengerId":280,
    "Survived":"1",
    "Pclass":3,
    "Sex":"female",
    "Age":35,
    "Fare":20.25
  },
  {
    "PassengerId":180,
    "Survived":"0",
    "Pclass":3,
    "Sex":"male",
    "Age":36,
    "Fare":0
  },
  {
    "PassengerId":664,
    "Survived":"0",
    "Pclass":3,
    "Sex":"male",
    "Age":36,
    "Fare":7.4958
  },
  {
    "PassengerId":190,
    "Survived":"0",
    "Pclass":3,
    "Sex":"male",
    "Age":36,
    "Fare":7.8958
  },
  {
    "PassengerId":606,
    "Survived":"0",
    "Pclass":3,
    "Sex":"male",
    "Age":36,
    "Fare":15.55
  },
  {
    "PassengerId":560,
    "Survived":"1",
    "Pclass":3,
    "Sex":"female",
    "Age":36,
    "Fare":17.4
  },
  {
    "PassengerId":596,
    "Survived":"0",
    "Pclass":3,
    "Sex":"male",
    "Age":36,
    "Fare":24.15
  },
  {
    "PassengerId":105,
    "Survived":"0",
    "Pclass":3,
    "Sex":"male",
    "Age":37,
    "Fare":7.925
  },
  {
    "PassengerId":504,
    "Survived":"0",
    "Pclass":3,
    "Sex":"female",
    "Age":37,
    "Fare":9.5875
  },
  {
    "PassengerId":466,
    "Survived":"0",
    "Pclass":3,
    "Sex":"male",
    "Age":38,
    "Fare":7.05
  },
  {
    "PassengerId":109,
    "Survived":"0",
    "Pclass":3,
    "Sex":"male",
    "Age":38,
    "Fare":7.8958
  },
  {
    "PassengerId":472,
    "Survived":"0",
    "Pclass":3,
    "Sex":"male",
    "Age":38,
    "Fare":8.6625
  },
  {
    "PassengerId":26,
    "Survived":"1",
    "Pclass":3,
    "Sex":"female",
    "Age":38,
    "Fare":31.3875
  },
  {
    "PassengerId":529,
    "Survived":"0",
    "Pclass":3,
    "Sex":"male",
    "Age":39,
    "Fare":7.925
  },
  {
    "PassengerId":401,
    "Survived":"1",
    "Pclass":3,
    "Sex":"male",
    "Age":39,
    "Fare":7.925
  },
  {
    "PassengerId":812,
    "Survived":"0",
    "Pclass":3,
    "Sex":"male",
    "Age":39,
    "Fare":24.15
  },
  {
    "PassengerId":886,
    "Survived":"0",
    "Pclass":3,
    "Sex":"female",
    "Age":39,
    "Fare":29.125
  },
  {
    "PassengerId":611,
    "Survived":"0",
    "Pclass":3,
    "Sex":"female",
    "Age":39,
    "Fare":31.275
  },
  {
    "PassengerId":14,
    "Survived":"0",
    "Pclass":3,
    "Sex":"male",
    "Age":39,
    "Fare":31.275
  },
  {
    "PassengerId":662,
    "Survived":"0",
    "Pclass":3,
    "Sex":"male",
    "Age":40,
    "Fare":7.225
  },
  {
    "PassengerId":562,
    "Survived":"0",
    "Pclass":3,
    "Sex":"male",
    "Age":40,
    "Fare":7.8958
  },
  {
    "PassengerId":41,
    "Survived":"0",
    "Pclass":3,
    "Sex":"female",
    "Age":40,
    "Fare":9.475
  },
  {
    "PassengerId":189,
    "Survived":"0",
    "Pclass":3,
    "Sex":"male",
    "Age":40,
    "Fare":15.5
  },
  {
    "PassengerId":361,
    "Survived":"0",
    "Pclass":3,
    "Sex":"male",
    "Age":40,
    "Fare":27.9
  },
  {
    "PassengerId":526,
    "Survived":"0",
    "Pclass":3,
    "Sex":"male",
    "Age":40.5,
    "Fare":7.75
  },
  {
    "PassengerId":154,
    "Survived":"0",
    "Pclass":3,
    "Sex":"male",
    "Age":40.5,
    "Fare":14.5
  },
  {
    "PassengerId":762,
    "Survived":"0",
    "Pclass":3,
    "Sex":"male",
    "Age":41,
    "Fare":7.125
  },
  {
    "PassengerId":861,
    "Survived":"0",
    "Pclass":3,
    "Sex":"male",
    "Age":41,
    "Fare":14.1083
  },
  {
    "PassengerId":255,
    "Survived":"0",
    "Pclass":3,
    "Sex":"female",
    "Age":41,
    "Fare":20.2125
  },
  {
    "PassengerId":639,
    "Survived":"0",
    "Pclass":3,
    "Sex":"female",
    "Age":41,
    "Fare":39.6875
  },
  {
    "PassengerId":846,
    "Survived":"0",
    "Pclass":3,
    "Sex":"male",
    "Age":42,
    "Fare":7.55
  },
  {
    "PassengerId":700,
    "Survived":"0",
    "Pclass":3,
    "Sex":"male",
    "Age":42,
    "Fare":7.65
  },
  {
    "PassengerId":198,
    "Survived":"0",
    "Pclass":3,
    "Sex":"male",
    "Age":42,
    "Fare":8.4042
  },
  {
    "PassengerId":350,
    "Survived":"0",
    "Pclass":3,
    "Sex":"male",
    "Age":42,
    "Fare":8.6625
  },
  {
    "PassengerId":819,
    "Survived":"0",
    "Pclass":3,
    "Sex":"male",
    "Age":43,
    "Fare":6.45
  },
  {
    "PassengerId":669,
    "Survived":"0",
    "Pclass":3,
    "Sex":"male",
    "Age":43,
    "Fare":8.05
  },
  {
    "PassengerId":679,
    "Survived":"0",
    "Pclass":3,
    "Sex":"female",
    "Age":43,
    "Fare":46.9
  },
  {
    "PassengerId":415,
    "Survived":"1",
    "Pclass":3,
    "Sex":"male",
    "Age":44,
    "Fare":7.925
  },
  {
    "PassengerId":604,
    "Survived":"0",
    "Pclass":3,
    "Sex":"male",
    "Age":44,
    "Fare":8.05
  },
  {
    "PassengerId":697,
    "Survived":"0",
    "Pclass":3,
    "Sex":"male",
    "Age":44,
    "Fare":8.05
  },
  {
    "PassengerId":161,
    "Survived":"0",
    "Pclass":3,
    "Sex":"male",
    "Age":44,
    "Fare":16.1
  },
  {
    "PassengerId":130,
    "Survived":"0",
    "Pclass":3,
    "Sex":"male",
    "Age":45,
    "Fare":6.975
  },
  {
    "PassengerId":277,
    "Survived":"0",
    "Pclass":3,
    "Sex":"female",
    "Age":45,
    "Fare":7.75
  },
  {
    "PassengerId":339,
    "Survived":"1",
    "Pclass":3,
    "Sex":"male",
    "Age":45,
    "Fare":8.05
  },
  {
    "PassengerId":363,
    "Survived":"0",
    "Pclass":3,
    "Sex":"female",
    "Age":45,
    "Fare":14.4542
  },
  {
    "PassengerId":168,
    "Survived":"0",
    "Pclass":3,
    "Sex":"female",
    "Age":45,
    "Fare":27.9
  },
  {
    "PassengerId":204,
    "Survived":"0",
    "Pclass":3,
    "Sex":"male",
    "Age":45.5,
    "Fare":7.225
  },
  {
    "PassengerId":593,
    "Survived":"0",
    "Pclass":3,
    "Sex":"male",
    "Age":47,
    "Fare":7.25
  },
  {
    "PassengerId":874,
    "Survived":"0",
    "Pclass":3,
    "Sex":"male",
    "Age":47,
    "Fare":9
  },
  {
    "PassengerId":133,
    "Survived":"0",
    "Pclass":3,
    "Sex":"female",
    "Age":47,
    "Fare":14.5
  },
  {
    "PassengerId":772,
    "Survived":"0",
    "Pclass":3,
    "Sex":"male",
    "Age":48,
    "Fare":7.8542
  },
  {
    "PassengerId":737,
    "Survived":"0",
    "Pclass":3,
    "Sex":"female",
    "Age":48,
    "Fare":34.375
  },
  {
    "PassengerId":598,
    "Survived":"0",
    "Pclass":3,
    "Sex":"male",
    "Age":49,
    "Fare":0
  },
  {
    "PassengerId":483,
    "Survived":"0",
    "Pclass":3,
    "Sex":"male",
    "Age":50,
    "Fare":8.05
  },
  {
    "PassengerId":632,
    "Survived":"0",
    "Pclass":3,
    "Sex":"male",
    "Age":51,
    "Fare":7.0542
  },
  {
    "PassengerId":407,
    "Survived":"0",
    "Pclass":3,
    "Sex":"male",
    "Age":51,
    "Fare":7.75
  },
  {
    "PassengerId":223,
    "Survived":"0",
    "Pclass":3,
    "Sex":"male",
    "Age":51,
    "Fare":8.05
  },
  {
    "PassengerId":153,
    "Survived":"0",
    "Pclass":3,
    "Sex":"male",
    "Age":55.5,
    "Fare":8.05
  },
  {
    "PassengerId":95,
    "Survived":"0",
    "Pclass":3,
    "Sex":"male",
    "Age":59,
    "Fare":7.25
  },
  {
    "PassengerId":327,
    "Survived":"0",
    "Pclass":3,
    "Sex":"male",
    "Age":61,
    "Fare":6.2375
  },
  {
    "PassengerId":484,
    "Survived":"1",
    "Pclass":3,
    "Sex":"female",
    "Age":63,
    "Fare":9.5875
  },
  {
    "PassengerId":281,
    "Survived":"0",
    "Pclass":3,
    "Sex":"male",
    "Age":65,
    "Fare":7.75
  },
  {
    "PassengerId":117,
    "Survived":"0",
    "Pclass":3,
    "Sex":"male",
    "Age":70.5,
    "Fare":7.75
  },
  {
    "PassengerId":852,
    "Survived":"0",
    "Pclass":3,
    "Sex":"male",
    "Age":74,
    "Fare":7.775
  }
]